{"count": 100, "comments": [{"rating": {"max": 5, "value": 5.0, "min": 0}, "useful_count": 178, "author": {"uid": "Camus", "avatar": "https://img1.doubanio.com\/icon\/u1075849-9.jpg", "signature": "\u4e0d\u8981\u903c\ufffd\u6211\u52a0\u7279\u6280", "alt": "https:\/\/www.douban.com\/people\/Camus\/", "id": "1075849", "name": "\u951f\u65a4\u62f7"}, "subject_id": "1303418", "content": "\u559c\u5267\u7535\u5f71\u5206\u4e24\u79cd\uff1a\u4e00\u79cd\u662f\u5218\u522b\u8c26\u73a9\u8fc7\u7684\uff0c\u4e00\u79cd\u662f\u5218\u522b\u8c26\u73a9\u5269\u4e0b\u7684", "created_at": "2011-05-12 00:52:43", "id": "387711287"}, {"rating": {"max": 5, "value": 5.0, "min": 0}, "useful_count": 78, "author": {"uid": "vanillacy", "avatar": "https://img3.doubanio.com\/icon\/u1104716-71.jpg", "signature": "\u5728\u6728\u9999\u82b1\u76db\u5f00\u7684\u51c9\u4ead\u4e0b", "alt": "https:\/\/www.douban.com\/people\/vanillacy\/", "id": "1104716", "name": "\u79bb\u9999"}, "subject_id": "1303418", "content": "If you prick us, do we not bleed? If you tickle us, do we not laugh?\u3000If you poison us, do we not die?\u3000If you wrong us, shall we not revenge?", "created_at": "2010-04-25 20:00:17", "id": "109161381"}, {"rating": {"max": 5, "value": 5.0, "min": 0}, "useful_count": 66, "author": {"uid": "inameless", "avatar": "https://img3.doubanio.com\/icon\/u1562273-521.jpg", "signature": "", "alt": "https:\/\/www.douban.com\/people\/inameless\/", "id": "1562273", "name": "\u54c1\u5ba2"}, "subject_id": "1303418", "content": "\u4e4b\u524d\u5728\u300a\u5e0c\u7279\u52d2\u4e07\u5c81\uff0c\u732a\u6b7b\u4e86\uff01\u300b\u4e00\u4e66\u4e2d\u8bfb\u5230\u6b64\u7247\u7684\u4ecb\u7ecd\uff0c\u4eca\u7ec8\u4e8e\u4e00\u7779\u5176\u98ce\u91c7\u3002\u6211\u5728\u5348\u591c4\u70b9\u975e\u5e38\u4eab\u53d7\u8fd9\u90e869\u5e74\u524d\u7684\u7535\u5f71\uff0c\u51e0\u4e4e\u7b11\u5230\u65ad\u6c14\u3002\u7cbe\u5f69\u7684\u5267\u60c5\uff0c\u6218\u4e89\u7684\u8bbd\u523a\uff0c\u8ba9\u4eba\u55b7\u996d\u7684\u7b11\u70b9\u3001\u53f0\u8bcd\uff0c\u5927\u5e08\u5218\u522b\u8c26\u7684\u6307\u5bfc\uff0c\u8fd9\u662f\u4f60\u4e00\u751f\u4e2d\u4e0d\u53ef\u4e0d\u770b\u7684\u7535\u5f71\u3002\u526f\u4f5c\u7528\u662f\u4eca\u540e\u5f53\u4f60\u542c\u5230\uff1a\u201c\u662f\u751f\u5b58\u8fd8\u662f\u6bc1\u706d\u201d\u8fd9\u53e5\u7ecf\u5178\u53f0\u8bcd\u65f6\uff0c\u4f1a\u7206\u7b11\u3002", "created_at": "2011-04-17 05:26:16", "id": "274528305"}, {"rating": {"max": 5, "value": 5.0, "min": 0}, "useful_count": 45, "author": {"uid": "yuanmu", "avatar": "https://img3.doubanio.com\/icon\/u1850420-142.jpg", "signature": "\u516c\u4f17\u53f7\uff1ayuanmufm", "alt": "https:\/\/www.douban.com\/people\/yuanmu\/", "id": "1850420", "name": "\u8881\u7267"}, "subject_id": "1303418", "content": "\u201c\u6211\u771f\u8ba8\u538c\u628a\u6211\u4eec\u56fd\u5bb6\u7684\u547d\u8fd0\u4ea4\u5230\u7b28\u6f14\u5458\u7684\u624b\u91cc\u201c\uff0c\u6700\u4e50\u7684\u90e8\u5206\u662f\u6b63\u4e54\u88c5\u7eb3\u7cb9\u7684\u6f14\u5458\u4f1a\u5ffd\u7136\u5206\u4e0d\u6e05\u620f\u5185\u5916\u7684\u8eab\u4efd\uff0c\u6f14\u54c8\u59c6\u83b1\u7279\u65f6\u53f0\u4e0b\u603b\u8981\u91cd\u590d\u8df3\u51fa\u4e9b\u559c\u5267\u72b6\u51b5\uff0c\u5938\u5f20\u3001\u89e3\u6784\u3001\u53cd\u8bbd\u3001\u5229\u7528\u5de7\u5408\uff0c\u60f3\u6f14\u300a\u5a01\u5c3c\u65af\u5546\u4eba\u300b\u7684\u9f99\u5957\u6f14\u5458\u5728\u4e0d\u8d77\u773c\u7684\u5783\u573e\u65f6\u95f4\u5ff5\u4e86\u51e0\u6b21\u590f\u6d1b\u514b\u7684\u63a7\u8bc9\uff0c\u7eaf\u5c5e\u5939\u5e26\u79c1\u8d27\uff0c\u662f\u72b9\u592a\u5bfc\u6f14\u5185\u5fc3\u6700\u6df1\u6700\u771f\u7684\u6124\u6012\u5427", "created_at": "2011-12-10 22:12:14", "id": "467699418"}, {"rating": {"max": 5, "value": 3.0, "min": 0}, "useful_count": 109, "author": {"uid": "tjz230", "avatar": "https://img1.doubanio.com\/icon\/u1005928-127.jpg", "signature": "", "alt": "https:\/\/www.douban.com\/people\/tjz230\/", "id": "1005928", "name": "\u5f71\u5fd7"}, "subject_id": "1303418", "content": "\u8138\u76f2\u8005\u614e\u770b", "created_at": "2012-11-03 20:45:17", "id": "598967798"}, {"rating": {"max": 5, "value": 5.0, "min": 0}, "useful_count": 35, "author": {"uid": "Zizou_Vam", "avatar": "https://img1.doubanio.com\/icon\/u4403626-327.jpg", "signature": "One Faithful Hahatologist", "alt": "https:\/\/www.douban.com\/people\/Zizou_Vam\/", "id": "4403626", "name": "\u6258\u5c3c\u00b7\u738b\u5927\u62ff"}, "subject_id": "1303418", "content": "\u59cb\u7956\u7ea7\u7684\u620f\u4e2d\u620f\uff0c\u65e0\u8bba\u662f\u73af\u73af\u76f8\u6263\u7684\u60c5\u8282\u8fd8\u662f\u5b57\u5b57\u73e0\u7391\u7684\u53f0\u8bcd\u90fd\u5df2\u7ecf\u8d85\u795e\uff1b\u770b\u5b8c\u8fd9\u79cd\u7535\u5f71\u4f1a\u8ba9\u4eba\u8bed\u8a00\u8d2b\u4e4f\uff0c\u53ea\u80fd\u9ed8\u9ed8\u5728\u5fc3\u91cc\u5927\u53eb\u4e00\u58f0\u597d\u3002", "created_at": "2013-05-05 23:12:05", "id": "676713735"}, {"rating": {"max": 5, "value": 5.0, "min": 0}, "useful_count": 25, "author": {"uid": "Jia-Z", "avatar": "https://img3.doubanio.com\/icon\/u28740126-6.jpg", "signature": "\u70e7\u83dc\u901b\u83dc\u573a", "alt": "https:\/\/www.douban.com\/people\/Jia-Z\/", "id": "28740126", "name": "\u516b\u6212"}, "subject_id": "1303418", "content": "To Be or Not to Be\uff0c\u571f\u9cd6\u62d7\u5b6c\u571f\u9cd6\uff0c\u5218\u522b\u8c26\u5bfc\u6f14\u4f5c\u54c1\uff0c1942\u5e74\u7684\u9ed1\u767d\u7247\uff0c\u6559\u79d1\u4e66\u822c\u7684\u6770\u4f5c\uff0c\u544a\u8bc9\u4f60\u4e00\u4e2a\u5267\u56e2\u600e\u4e48\u4ee5\u81ea\u5df1\u65b9\u5f0f\u611a\u5f04\u7b2c\u4e09\u5e1d\u56fd\uff0c\u6b63\u4e49\u600e\u4e48\u6b3a\u8d1f\u90aa\u6076\u3002\u773c\u775b\u4e00\u7728\uff0c\u8001\u6bcd\u9e21\u53d8\u9e2d\uff0c\u5728\u8fd9\u7535\u5f71\u4e0a\u8017\u8d39\u6bcf\u4e00\u5206\u949f\u90fd\u662f\u503c\u5f97\u7684\uff0c\u56e0\u4e3a\u5145\u6ee1\u4e86\u9b54\u672f\u822c\u7684\u9006\u8f6c\u548c\u6742\u800d\u822c\u7684\u72c2\u6b22\u3002\u2014\u2014\u9e66\u9e49\u53f2\u822a\r\n", "created_at": "2012-10-06 20:39:38", "id": "588280921"}, {"rating": {"max": 5, "value": 5.0, "min": 0}, "useful_count": 26, "author": {"uid": "conanemily", "avatar": "https://img3.doubanio.com\/icon\/u4416375-53.jpg", "signature": "wx\u516c\u5171\u53f7\uff1a\u7c73\u7c92\u7535\u5f71\u9662", "alt": "https:\/\/www.douban.com\/people\/conanemily\/", "id": "4416375", "name": "\u7c73\u7c92"}, "subject_id": "1303418", "content": "\u7b80\u76f4\u7206\u7b11\u554a\uff01\u8fd9\u624d\u662f\u597d\u559c\u5267\u554a\uff0c\u7b11\u70b9\u4e00\u767e\u5e74\u4e0d\u8fc7\u65f6\uff01\u6bcf\u4e00\u79d2\u90fd\u6ee1\u5206\uff01", "created_at": "2014-03-14 11:01:16", "id": "785910219"}, {"rating": {"max": 5, "value": 0, "min": 0}, "useful_count": 13, "author": {"uid": "melody1971", "avatar": "https://img3.doubanio.com\/icon\/u1917650-835.jpg", "signature": "", "alt": "https:\/\/www.douban.com\/people\/melody1971\/", "id": "1917650", "name": "\u6e38\u7267\u4eba\u00b7\u82b3\u6c40"}, "subject_id": "1303418", "content": "\u4e00\u6ce2\u591a\u6298\uff0c\u5c42\u5c42\u63a8\u8fdb\uff0c\u7ec6\u8282\u5904\u5904\u8ff7\u4eba\uff0c\u4e25\u8083\u3001\u7d27\u5f20\u3001\u8bd9\u8c10\u5e76\u5b58\uff0c\u6709\u6211\u559c\u6b22\u7684\u4e00\u5207\u559c\u5267\u5143\u7d20\u3002\u5218\u522b\u8c26\u7684\u7edd\u5999\u53f0\u8bcd\u4ee4\u6211\u4e0d\u65ad\u5728\u6df1\u591c\u5927\u58f0\u53d1\u51fa\u9635\u9635\u60e8\u7b11\uff08\u5e0c\u671b\u6ca1\u6709\u592a\u6270\u6c11= =\uff09\u201c\u5979\u7684\u4e08\u592b\u662f\u4f1f\u5927\u7684\u6ce2\u5170\u6f14\u5458XXXXX\uff0c\u4f60\u4e00\u5b9a\u542c\u8bf4\u8fc7\u5427\u3002\u201d\u201c\u662f\u7684\uff0c\u6211\u770b\u8fc7\u4ed6\u7684\u821e\u53f0\u5267\uff0c\u4ed6\u5bf9\u838e\u58eb\u6bd4\u4e9a\u6240\u505a\u7684\u4e8b\u60c5\u5c31\u662f\u6211\u4eec\u7eb3\u7cb9\u73b0\u5728\u8981\u5bf9\u6ce2\u5170\u505a\u7684\u3002\u201d", "created_at": "2012-12-05 00:20:57", "id": "387215918"}, {"rating": {"max": 5, "value": 4.0, "min": 0}, "useful_count": 18, "author": {"uid": "55717894", "avatar": "https://img3.doubanio.com\/icon\/u55717894-70.jpg", "signature": "broken nerve", "alt": "https:\/\/www.douban.com\/people\/55717894\/", "id": "55717894", "name": "\u68a6\u4e2d\u7684D"}, "subject_id": "1303418", "content": "\u4e00\u6839\u7b4b\u7684\u918b\u575b\u5b50\u4e08\u592b\u4ee5\u9ad8\u8d85\u6f14\u6280\u62ef\u6551\u4e86\u4e00\u4e2a\u56fd\u5bb6\uff0c\u4e2a\u4e2d\u6865\u6bb5\u592a\u5e7d\u9ed8\u4e86", "created_at": "2012-09-08 00:45:25", "id": "577814719"}, {"rating": {"max": 5, "value": 5.0, "min": 0}, "useful_count": 28, "author": {"uid": "flowermumu", "avatar": "https://img3.doubanio.com\/icon\/u1147451-90.jpg", "signature": "", "alt": "https:\/\/www.douban.com\/people\/flowermumu\/", "id": "1147451", "name": "\u6b22\u4e50\u5206\u88c2"}, "subject_id": "1303418", "content": "\u7edd\u5999\u7684\u8bbd\u523a\u559c\u5267", "created_at": "2010-05-09 22:01:06", "id": "249194142"}, {"rating": {"max": 5, "value": 5.0, "min": 0}, "useful_count": 5, "author": {"uid": "songdynasty", "avatar": "https://img3.doubanio.com\/icon\/u44583352-26.jpg", "signature": "reductio ad absurdum", "alt": "https:\/\/www.douban.com\/people\/songdynasty\/", "id": "44583352", "name": "\u4e0a\u4e16\u7eaa\u7684\u4e91"}, "subject_id": "1303418", "content": "\u5218\u522b\u8c26\u662f\u4e2a\u5fb7\u56fd\u4eba\uff0c1942\u5e74\u4e8c\u6218\u8fd8\u6ca1\u7ed3\u675f\u5c31\u5728\u7f8e\u56fd\u62cd\u4e86\u90e8\u8bbd\u523a\u7eb3\u7cb9\u5fb7\u56fd\u7684\u559c\u5267\u7247\u3002\u66f4\u91cd\u8981\u7684\u662f\uff0c\u548c\u5353\u522b\u6797\u7684\u300a\u5927\u72ec\u88c1\u8005\u300b\u6bd4\u8d77\u6765\uff0c\u8fd9\u90e8\u559c\u5267\u7684\u7b11\u70b9\u66f4\u52a0\u9ad8\u7ea7\u3002\u5218\u522b\u8c26\u7535\u5f71\u7684\u9b45\u529b\u771f\u662f\u5947\u7279\u3002", "created_at": "2012-10-05 16:48:16", "id": "587772510"}, {"rating": {"max": 5, "value": 5.0, "min": 0}, "useful_count": 22, "author": {"uid": "drtsb", "avatar": "https://img3.doubanio.com\/icon\/u1420054-34.jpg", "signature": "\u6368\u4e0d\u5f97\u96e2\u958b\u5c0d\u5c0d\u96d9\u96d9", "alt": "https:\/\/www.douban.com\/people\/drtsb\/", "id": "1420054", "name": "Margo"}, "subject_id": "1303418", "content": "\u65af\u57fa\u5927\u5718\u805a...\u5289\u5225\u8b19\u842c\u6b72", "created_at": "2010-03-04 18:39:45", "id": "224623183"}, {"rating": {"max": 5, "value": 5.0, "min": 0}, "useful_count": 5, "author": {"uid": "muthologikos", "avatar": "https://img3.doubanio.com\/icon\/u56907760-4.jpg", "signature": "", "alt": "https:\/\/www.douban.com\/people\/muthologikos\/", "id": "56907760", "name": "\u827e\u6d1b"}, "subject_id": "1303418", "content": "LUBITSCH\u4e07\u5c81\u3002\u5927\u7b11\u8fc7\u4e4b\u540e\u60f3\u8d77\u90a3\u4e2a\u603b\u662f\u8dd1\u9f99\u5957\u6f14\u914d\u89d2\u7684\u6f14\u5458\uff0c\u4ed6\u4e00\u76f4\u89c9\u5f97\u81ea\u5df1\u80fd\u6f14\u597d\u590f\u6d1b\u514b\uff0c\u540c\u4f34\u603b\u662f\u5632\u7b11\u4ed6\u4e00\u756a\uff0c\u540e\u6765\u5bb6\u56ed\u88ab\u5fb7\u56fd\u4eba\u5360\u9886\uff0c\u4e24\u4eba\u8fde\u9f99\u5957\u90fd\u8dd1\u4e0d\u4e86\uff0c\u5728\u8857\u4e0a\u94f2\u96ea\u7684\u65f6\u5019\uff0c\u4ed6\u53c8\u80cc\u8bf5\u8d77\u590f\u6d1b\u514b\u90a3\u6bb5\u7ecf\u5178\u7684\u53f0\u8bcd\uff0c\u8fd9\u6b21\u540c\u4f34\u8bf4\uff0c\u4f60\u80fd\u6f14\u597d\u590f\u6d1b\u514b\u4e86\u3002\u7ecf\u5386\u8fc7\u90a3\u4e9b\u75db\u82e6\u6124\u6012\u4e4b\u540e\uff0c\u6211\u4eec\u624d\u80fd\u771f\u7684\u5199\u51fa\u8bfb\u51fa\u90a3\u4e9b\u8bd7\u884c\u5427", "created_at": "2013-11-16 03:10:44", "id": "745215499"}, {"rating": {"max": 5, "value": 5.0, "min": 0}, "useful_count": 4, "author": {"uid": "luzhiyu", "avatar": "https://img3.doubanio.com\/icon\/u2866549-132.jpg", "signature": "\u56e0\u4e3a\u4f60\u6d3b\u7740\uff0c\u6240\u4ee5\u662f\u7ea2\u8272\u7684\u3002", "alt": "https:\/\/www.douban.com\/people\/luzhiyu\/", "id": "2866549", "name": "\u9646\u652f\u7fbd"}, "subject_id": "1303418", "content": "5.0\u30021.\u5218\u522b\u8c26\u7edd\u4e16\u7ecf\u5178\u8bbd\u523a\u559c\u5267\uff0c\u4f46\u76f8\u6bd4\u4e4b\u4e0b\uff0c\u6211\u8fd8\u662f\u66f4\u7231[\u7389\u5973\u98ce\u6d41]\u54ce\u30022.\u620f\u4e2d\u620f\uff1a\u4ee5\u6f14\u620f\u65b9\u5f0f\u9003\u79bb\u7eb3\u7cb9\u9b54\u638c\uff0c\u4e3a\u540e\u4e16\u6367\u8a89\u81f3\u4eca\u30023.\u62d0\u89d2\u89c2\u5f71\uff0c\u7b2c11\u8db4\u3002", "created_at": "2014-04-14 21:24:52", "id": "367425909"}, {"rating": {"max": 5, "value": 4.0, "min": 0}, "useful_count": 4, "author": {"uid": "liusuer", "avatar": "https://img3.doubanio.com\/icon\/u42392653-10.jpg", "signature": "\u516c\u53f7\uff1a\u5468\u51b2\u7684\u5f71\u50cf\u58f0\u8272", "alt": "https:\/\/www.douban.com\/people\/liusuer\/", "id": "42392653", "name": "\u5468\u51b2"}, "subject_id": "1303418", "content": "\u771f\u7684\u975e\u5e38\u6709\u610f\u601d\u3002\u8bbe\u8ba1\u5f97\u5f88\u5de7\u5999\uff0c\u4e0d\u523b\u610f\uff0c\u4e0d\u751f\u786c\uff0c\u4e0d\u843d\u7aa0\u81fc", "created_at": "2011-05-12 16:10:18", "id": "389372220"}, {"rating": {"max": 5, "value": 5.0, "min": 0}, "useful_count": 9, "author": {"uid": "iorl", "avatar": "https://img3.doubanio.com\/icon\/u2049771-372.jpg", "signature": "\u5c0f\u857e\u6df1\u85cf\u6570\u70b9\u7ea2\u3002", "alt": "https:\/\/www.douban.com\/people\/iorl\/", "id": "2049771", "name": "\u82b1\u513f\u679c\u679c"}, "subject_id": "1303418", "content": "\u65e9\u770b\u8fc783\u5e74\u7684\u7ffb\u62cd\u7248\uff0c\u91cd\u770b61\u7248\uff0c\u66f4\u5f70\u663e\u5218\u522b\u8c26\u7684\u5320\u5fc3\u72ec\u5177\uff01", "created_at": "2010-08-29 15:12:50", "id": "287812881"}, {"rating": {"max": 5, "value": 5.0, "min": 0}, "useful_count": 2, "author": {"uid": "yalindongdong", "avatar": "https://img3.doubanio.com\/icon\/u2586116-96.jpg", "signature": "Life is wonderful !", "alt": "https:\/\/www.douban.com\/people\/yalindongdong\/", "id": "2586116", "name": "\u65b9\u67aa\u67aa"}, "subject_id": "1303418", "content": "\u620f\u4e2d\u620f\u5f00\u59cb\u4e4b\u540e\u6574\u4e2a\u7535\u5f71\u5c31\u53d8\u5f97\u597d\u73a9\u6709\u8da3\u591a\u4e86\uff0c\u591a\u91cd\u5de7\u5408\uff0c\u5faa\u73af\u5f80\u590d\u7684\u53d9\u4e8b\uff0c\u6f14\u5458\u9017\u8da3\u5e7d\u9ed8\u7684\u8868\u6f14\uff0c\u5341\u8db3\u4e00\u4e2a\u821e\u53f0\u5267\u7248\u7684\u300a\u864e\u53e3\u8131\u9669\u300b\uff0c\u4e00\u4e2a\u5267\u56e2\u73a9\u5f04\u4e86\u4e00\u7fa4\u7eb3\u7cb9\uff0c\u5bfc\u6f14\u4e5f\u73a9\u7684\u6d12\u8131\uff0c\u6d3b\u8131\u8131\u628a\u4e00\u5e55\u60ca\u9669\u523a\u6fc0\u7684\u8c0d\u6218\u7ed9\u62cd\u6210\u4e86\u7ecf\u5178\u559c\u5267\u3002\u9017\u6781\u4e86\u3002\u6c38\u8fdc\u4e5f\u5fd8\u4e0d\u4e86\u54c8\u59c6\u96f7\u7279\u8bf4\u5b8c\u201cTo Be or Not to Be\u201d\u540e\u6709\u4eba\u79bb\u5f00\u90a3\u5e7d\u6028\u7684\u773c\u795e", "created_at": "2016-10-15 17:02:35", "id": "678584737"}, {"rating": {"max": 5, "value": 4.0, "min": 0}, "useful_count": 2, "author": {"uid": "zhiliaofly", "avatar": "https://img3.doubanio.com\/icon\/u1206028-16.jpg", "signature": "", "alt": "https:\/\/www.douban.com\/people\/zhiliaofly\/", "id": "1206028", "name": "\u5439\u98ce\u6563\u6b65"}, "subject_id": "1303418", "content": "\u5b9e\u4e8b\u6c42\u662f\u7684\u8bf4\uff0c\u65b0\u7248\u7531\u4e8e\u8fc7\u4e8e\u8ffd\u6c42\u5267\u60c5\u7684\u5408\u7406\u6027\uff0c\u53cd\u800c\u4ee4\u65e7\u7684\u559c\u5267\u6865\u6bb5\u5728\u65b0\u7248\u4e2d\u663e\u5f97\u8fc7\u4e8e\u7a81\u5140\u3002\u800c\u5218\u522b\u8c26\u7684\u7248\u672c\u56e0\u4e3a\u539f\u521b\u7684\u7f18\u6545\u66f4\u5bb9\u6613\u8ba9\u5927\u591a\u6570\u4eba\u8ba4\u53ef\uff0c\u4e2a\u4eba\u8ba4\u4e3aBrooks\u6781\u5f3a\u7684\u8868\u73b0\u529b\u8ba9\u539f\u672c\u8352\u8bde\u7684\u6545\u4e8b\u60c5\u8282\u66f4\u6709\u5f20\u529b\uff0c\u65e7\u7248\u7684\u4f18\u52bf\u4e5f\u662f\u663e\u800c\u6613\u89c1\u7684\uff0c\u6709\u4e00\u4e2a\u7b26\u5408\u5267\u60c5\u63cf\u8ff0\u7684\u7f8e\u4e3d\u5973\u4e3b\u89d2\uff0c\u800c\u65b0\u7248\u8001\u5e03\u7684\u592a\u592a\u660e\u663e\u5e74\u534e\u901d\u53bb\u4e86\u3002", "created_at": "2011-07-30 00:49:16", "id": "254649746"}, {"rating": {"max": 5, "value": 4.0, "min": 0}, "useful_count": 1, "author": {"uid": "taotaomvp", "avatar": "https://img3.doubanio.com\/icon\/u4471722-4.jpg", "signature": "\u5fd7\u7707\u7707\u800c\u4e34\u4e91", "alt": "https:\/\/www.douban.com\/people\/taotaomvp\/", "id": "4471722", "name": "\u82b1\u5c9b\u4ed9\u85cf"}, "subject_id": "1303418", "content": "\u53cd\u8f6c\u518d\u53cd\u8f6c\uff0c\u597d\u73a9\u3002Jack Benny\u8001\u4e86\u957f\u6b8b\u4e86\uff0c\u4e0d\u8fc7\u773c\u795e\u8fd8\u662f\u5f88\u9017\u8da3\u3002Robert Stack\u6f14\u8fd9\u90e8\u7684\u65f6\u5019\u624d23\u5c81\uff0c\u82f1\u4fca\u6b7b\u4e86\uff0c\u8981\u547d\u554a(\u00af\ufe43\u00af)", "created_at": "2015-08-25 17:33:02", "id": "953279925"}, {"rating": {"max": 5, "value": 5.0, "min": 0}, "useful_count": 0, "author": {"uid": "sampaning", "avatar": "https://img3.doubanio.com\/icon\/u1410853-44.jpg", "signature": "Byebye\u5662\uff0cByebye\u5566\u2026\u2026", "alt": "https:\/\/www.douban.com\/people\/sampaning\/", "id": "1410853", "name": "\u6487\u6a2a\u6a2a\u7ad6"}, "subject_id": "1303418", "content": "\u7cbe\u5f69\u7684\u559c\u5267\uff0c\u673a\u667a\u98ce\u8da3\uff0c\u53f0\u8bcd\u771f\u6f02\u4eae\u3002\u7b2c\u4e00\u6b21\u770b\u5218\u522b\u8c26\uff0c\u7b2c\u4e00\u6b21\u542c\u5230\u8fd9\u4e2a\u8bcd\u201c\u5218\u522b\u8c26\u5f0f\u89e6\u52a8\u201d\uff08Lubitsch Touch) \uff0c\u5174\u8da3\u987f\u751f\u3002", "created_at": "2010-03-17 22:24:54", "id": "230096485"}, {"rating": {"max": 5, "value": 5.0, "min": 0}, "useful_count": 0, "author": {"uid": "masaikejun", "avatar": "https://img3.doubanio.com\/icon\/u45460966-6.jpg", "signature": "\u6a21\u7cca\u3001\u54b8\u6e7f\u3001\u4e00\u68a6\u4f3c\u957f\u6b4c", "alt": "https:\/\/www.douban.com\/people\/masaikejun\/", "id": "45460966", "name": "\u9a6c\u8d5b\u514b"}, "subject_id": "1303418", "content": "\u54c8\u54c8\u54c8\uff0c\u4e8c\u6218\u65f6\u7684\u559c\u5267\u4e5f\u8d85\u6709\u610f\u601d\u554a\uff0c\u867d\u7136\u5bf9\u654c\u5bf9\u56fd\u7684\u7eb3\u7cb9\u6709\u4e9b\u4e11\u5316\uff0c\u4f46\u662f\u7b11\u6599\u628a\u63e1\u7684\u5f88\u597d\uff0c\u6574\u4e2a\u7535\u5f71\u7684\u8282\u594f\u7d27\u5f20\u523a\u6fc0\uff0c\u6700\u540e\u7684\u79bb\u573a\u7b11\u70b9\u76f8\u5f53\u6709\u610f\u601d\u3002\u8fd9\u8981\u662f\u7ffb\u62cd\u7684\u8bdd\u4f30\u8ba1\u5c31\u6210\u4e86\u65e0\u803b\u6df7\u86cb+\u864e\u53e3\u9003\u751f\u4e86\uff0c\u8001\u7535\u5f71\u679c\u7136\u6b22\u4e50\u591a\u554a~", "created_at": "2012-12-08 21:31:42", "id": "611318475"}, {"rating": {"max": 5, "value": 5.0, "min": 0}, "useful_count": 0, "author": {"uid": "longzheking", "avatar": "https://img1.doubanio.com\/icon\/u4285566-29.jpg", "signature": "\u7a81\u7136\u5c31\u4e07\u5ff5\u4ff1\u7070\u4e86\uff0c\u515a\u90fd\u6321\u4e0d\u4f4f", "alt": "https:\/\/www.douban.com\/people\/longzheking\/", "id": "4285566", "name": "\u6c6a\u91d1\u536b"}, "subject_id": "1303418", "content": "\u30102013\u5e74\u7b2c400\u90e8\u7535\u5f71\u732e\u7ed9\u5218\u522b\u8c26\u30111942\u5e74\u7684\u8bbd\u523a\u7eb3\u7cb9\u7684\u559c\u5267\u3002\u975e\u5e38\u7cbe\u81f4\u800c\u641e\u7b11\u3002\u7cbe\u5fc3\u8bbe\u8ba1\u53c8\u81ea\u7136\u7684\u7b11\u70b970\u5e74\u540e\u4f9d\u65e7\u8ba9\u4eba\u6367\u8179\u3002\u56de\u5473\u65e0\u7a77\u3002\u80fd\u770b\u5230\u5f88\u591a\u540e\u4e16\u7535\u5f71\u7684\u5f71\u5b50\uff1a\u300a\u65e0\u803b\u6df7\u86cb\u300b\u7684\u620f\u8c11\u5143\u9996\uff1b\u300a\u789f\u4e2d\u8c0d4\u300b\u7684\u5de6\u53f3\u9022\u6e90\u7b49\u3002\u539f\u6765\u90fd\u662f\u5218\u522b\u8c26\u73a9\u5269\u4e0b\u7684\u3002\u53ef\u4e0e\u300a\u5927\u72ec\u88c1\u8005\u300b\u76f8\u5ab2\u7f8e\u3002\u4f46\u8fd8\u662f\u4e0d\u5982\u5176\u4f1f\u5927\u800c\u4e0d\u673d\u3002\u56db\u661f\u534a", "created_at": "2013-11-13 20:14:37", "id": "349796652"}, {"rating": {"max": 5, "value": 5.0, "min": 0}, "useful_count": 0, "author": {"uid": "2432383", "avatar": "https://img1.doubanio.com\/icon\/u2432383-7.jpg", "signature": "", "alt": "https:\/\/www.douban.com\/people\/2432383\/", "id": "2432383", "name": "zym16zym"}, "subject_id": "1303418", "content": "\u7247\u5b50\u5728\u7535\u8111\u91cc\u653e\u4e00\u5e74\u4e86\uff0c\u4eca\u5929\u624d\u9759\u4e0b\u5fc3\u6765\u62dc\u8bfb\u5218\u522b\u8c26\u7684\u5927\u4f5c\uff0c\u7cbe\u5999\u7684\u526a\u8f91\uff0c\u7cbe\u5f69\u7684\u5bf9\u8bdd\uff0c\u5de7\u5999\u7684\u5267\u60c5\u3002\u8fd8\u526920\u5206\u949f\u7684\u65f6\u5019\u60f3\u6253\u56db\u9897\u661f\uff0c\u6700\u540e\u771f\u662f\u9ad8\u6f6e\u8fed\u8d77\uff0c\u5999\u4e0d\u53ef\u8a00\u3002\u8fd8\u6709\u5c31\u662f\u5973\u4e3b\u89d2\u7684\u8d34\u8eab\u5973\u4f63\u7b80\u76f4\u5c31\u662f\u5410\u69fd\u7684\u9f3b\u7956\uff0c\u518d\u6b21\u5411\u7ecf\u5178\u81f4\u656c", "created_at": "2012-09-01 17:57:36", "id": "575407106"}, {"rating": {"max": 5, "value": 4.0, "min": 0}, "useful_count": 2, "author": {"uid": "57184681", "avatar": "https://img3.doubanio.com\/icon\/u57184681-30.jpg", "signature": "\u6b63\u5b97\u5370\u5c3c\u71d5\u7a9d\u76f4\u9500", "alt": "https:\/\/www.douban.com\/people\/57184681\/", "id": "57184681", "name": "\u5370\u5c3c\u71d5\u7a9d\u5468\u638c\u67dc"}, "subject_id": "1303418", "content": "\u6807\u9898\u4e0e\u5185\u5bb9\u5951\u5408\u5f97\u5982\u6b64\u5929\u8863\u65e0\u7f1d \u800c\u53c8\u8da3\u5473\u76ce\u7136", "created_at": "2013-03-27 10:58:38", "id": "659440657"}, {"rating": {"max": 5, "value": 5.0, "min": 0}, "useful_count": 0, "author": {"uid": "ursula74", "avatar": "https://img3.doubanio.com\/icon\/u1957431-16.jpg", "signature": "Find me. Or I'll find u.", "alt": "https:\/\/www.douban.com\/people\/ursula74\/", "id": "1957431", "name": "Moning"}, "subject_id": "1303418", "content": "1941\u5e74\u82cf\u5fb7\u6218\u4e89\u7206\u53d1\u540e\u7eb3\u7cb9\u5fb7\u56fd\u5360\u9886\u6ce2\u5170\u5168\u5883\u3002\u6b21\u5e74\u5173\u4e8e\u7eb3\u7cb9\u4e0b\u7684\u6ce2\u5170\u5267\u56e2\u6551\u56fd\u7684\u559c\u5267\u7535\u5f71\u53d1\u884c\u3002\u5267\u56e2\u6f14\u7eb3\u7cb9\uff08\u201c\u4e25\u8083\u7684\u73b0\u5b9e\u4e3b\u4e49\u620f\u5267\u201d:P\uff09\u800c\u7eb3\u7cb9\u5728\u5f71\u7247\u4e2d\u6765\u5230\u534e\u6c99\u4e86\u3002\u591a\u91cd\u89d2\u8272\u626e\u6f14\uff0c\u620f\u91cc\u620f\u5916\u620f\u4e2d\u620f\u3002Maria\u771f\u662f\u540d\u6f14\u5728\u4e08\u592b\u60c5\u592b\u654c\u4eba\u9762\u524d\u53d8\u8138\u81ea\u5982\u3002\u4e0d\u60f3\u201c\u56fd\u5bb6\u88ab\u7b28\u6f14\u5458\u7ed9\u6bc1\u4e86\u201d :P\u3002\u6218\u573a\u785d\u70df\uff0c\u60c5\u573a\u6c14\u7130\u3002\u7cbe\u5f69\uff01", "created_at": "2013-09-08 06:40:17", "id": "724182693"}, {"rating": {"max": 5, "value": 5.0, "min": 0}, "useful_count": 0, "author": {"uid": "stknight", "avatar": "https://img3.doubanio.com\/icon\/u3026435-2.jpg", "signature": "Addicted to Film Noir", "alt": "https:\/\/www.douban.com\/people\/stknight\/", "id": "3026435", "name": "stknight"}, "subject_id": "1303418", "content": "\u6069\u65af\u7279\u00b7\u5218\u522b\u8c26\u7684\u7ecf\u5178\u559c\u5267\uff0c\u53ef\u80fd\u98ce\u683c\u4e0a\u4e0e\u4ed6\u7684\u5176\u4ed6\u5f71\u7247\u6709\u5f88\u5927\u533a\u522b\uff0c\u4e3b\u8981\u662f\u201c\u89e6\u89c9\u201d\u4f53\u73b0\u7684\u4e0d\u662f\u5f88\u591a\uff0c\u4e0d\u8fc7\u4f5c\u4e3a\u4e8c\u6218\u7ecf\u5178\u559c\u5267\u53ef\u662f\u6bd4\u300a\u864e\u53e3\u8131\u9669\u300b\u65e9\u4e86\u4e8c\u5341\u591a\u5e74\u3002\u6bd4\u5b83\u65e9\u4e00\u70b9\u7684\u300a\u5927\u72ec\u88c1\u8005\u300b\u7684\u6210\u529f\u4e3b\u8981\u5f52\u529f\u4e8e\u5353\u522b\u6797\u5bf9\u5e0c\u7279\u52d2\u795e\u4f3c\u7684\u6a21\u4eff\u548c\u5927\u80c6\u7684\u6076\u641e\uff0c\u800c\u300a\u4f60\u9003\u6211\u4e5f\u9003\u300b\u5219\u80dc\u5728\u60c5\u8282\u7684\u73af\u73af\u76f8\u6263\uff0c\u7d27\u5f20\u523a\u6fc0\u800c\u53c8\u5999\u8da3\u6a2a\u751f", "created_at": "2010-12-19 00:17:02", "id": "235183921"}, {"rating": {"max": 5, "value": 3.0, "min": 0}, "useful_count": 7, "author": {"uid": "HiddenParadise", "avatar": "https://img1.doubanio.com\/icon\/u1793566-1867.jpg", "signature": "\u4e00\u4e2a\u61d2\u764c\u60a3\u8005\u7684\u81ea\u7559\u5730", "alt": "https:\/\/www.douban.com\/people\/HiddenParadise\/", "id": "1793566", "name": "Urth\u00f3naD'Mors"}, "subject_id": "1303418", "content": "\u5f00\u5934\u505a\u7684\u53ef\u771f\u6709\u611f\u89c9", "created_at": "2010-11-28 23:33:56", "id": "320038790"}, {"rating": {"max": 5, "value": 5.0, "min": 0}, "useful_count": 0, "author": {"uid": "Reynard", "avatar": "https://img3.doubanio.com\/icon\/u2778132-23.jpg", "signature": "", "alt": "https:\/\/www.douban.com\/people\/Reynard\/", "id": "2778132", "name": "Reynard"}, "subject_id": "1303418", "content": "\u592a\u7ecf\u5178\u592a\u641e\u7b11\u4e86\uff0c\u7adf\u7136\u80fd\u628a\u4e00\u90e8\u7d27\u5f20\u523a\u6fc0\u7684\u5f71\u7247\u62cd\u5f97\u5982\u6b64\u641e\u7b11\u3002\u4e00\u5b9a\u8981\u770b\u82f1\u6587\u5b57\u5e55\u7684\uff0c\u80fd\u542c\u61c2\u7684\u8bdd\u76f4\u63a5\u542c\u82f1\u8bed\uff0c\u4e2d\u6587\u7ffb\u8bd1\u8fc7\u6765\u5c31\u4e0d\u90a3\u4e48\u641e\u7b11\u4e86\u3002\u5218\u522b\u8c26\u771f\u8ba9\u4eba\u89c1\u8bc6\u4e86\u3002\u53ef\u60dc\u7684\u662f\u6709\u4e9b\u6865\u6bb5\u8854\u63a5\u7684\u6709\u95ee\u9898\uff0c\u4e0d\u8fc7\u7455\u4e0d\u63a9\u745c\u5440", "created_at": "2011-04-22 22:32:15", "id": "381525308"}, {"rating": {"max": 5, "value": 4.0, "min": 0}, "useful_count": 0, "author": {"uid": "vivien_princess", "avatar": "https://img3.doubanio.com\/icon\/u43947990-142.jpg", "signature": "Greatest Love Of All ~~", "alt": "https:\/\/www.douban.com\/people\/vivien_princess\/", "id": "43947990", "name": "vivien"}, "subject_id": "1303418", "content": "\u5fb7\u56fd\u5bfc\u6f14\u4ee5\u8bd9\u8c10\u8c03\u4f83\u8bed\u8c03\u62cd\u4e86\u90e8\u4e8c\u6218\u82f1\u8bed\u7247\u3002\u7231\u56fd\u7684\u821e\u53f0\u6f14\u5458\u548c\u76d6\u4e16\u592a\u4fdd\u6697\u4e2d\u62b5\u6297\u3002\u626e\u6f14\u5e0c\u7279\u52d2\u5b9e\u5728\u641e\u7b11\u3002\u5973\u4e3b\u89d2\u662f\u76d6\u535a\u770b\u4e2d\u8fc7\u7684\u53ef\u60dc\u6b7b\u4e8e\u975e\u547d\u554a\u3002to be or not to be\u4f5c\u4e3a\u6697\u53f7\u592a\u6709\u65b0\u610f\u4e86\u3002", "created_at": "2012-04-29 20:31:25", "id": "525989717"}, {"rating": {"max": 5, "value": 5.0, "min": 0}, "useful_count": 1, "author": {"uid": "yuhuielf", "avatar": "https://img3.doubanio.com\/icon\/u1458911-15.jpg", "signature": "\u8981\u70ed\u7231\u751f\u6d3b", "alt": "https:\/\/www.douban.com\/people\/yuhuielf\/", "id": "1458911", "name": "mayfog"}, "subject_id": "1303418", "content": "\u5218\u522b\u8c26\u548cCarole Lambard\u3002\u559c\u5267\u548c\u60b2\u5267\u5e76\u5b58\uff0c\u7d27\u5f20\u548c\u6b22\u4e50\u5e76\u5728\uff0c\u8282\u594f\u5341\u5206\u7d27\u51d1\uff0c\u60c5\u8282\u4e5f\u51e0\u751f\u6ce2\u6298\u3002\u7535\u5f71\u7684\u5f00\u5934\u5f15\u4eba\u5165\u80dc\uff0c\u5c06\u201c\u620f\u4e2d\u620f\u201d\u7535\u5f71\u53d1\u6325\u5230\u4e86\u6781\u81f4\uff0c\u662f\u4e2a\u7cbe\u5fc3\u96d5\u7422\u7684\u597d\u6545\u4e8b\u3002Lambard33\u5c81\u5c31\u56e0\u98de\u673a\u5931\u4e8b\u53bb\u4e16\uff0c\u5979\u90a3\u65f6\u7684\u4e08\u592b\u514b\u62c9\u514b\u76d6\u535a\uff0c\u60b2\u75db\u6b32\u7edd\u3002\u76d6\u535a\u53bb\u4e16\u540e\uff0c\u5893\u7891\u5c31\u7acb\u5728\u524d\u59bb\u65c1\u8fb9\u3002", "created_at": "2011-01-02 02:54:39", "id": "334631726"}, {"rating": {"max": 5, "value": 4.0, "min": 0}, "useful_count": 9, "author": {"uid": "airan712", "avatar": "https://img3.doubanio.com\/icon\/u2492362-170.jpg", "signature": "", "alt": "https:\/\/www.douban.com\/people\/airan712\/", "id": "2492362", "name": "Q\u3002"}, "subject_id": "1303418", "content": "\u201cto be \u2026\u2026 or not to be\u2026\u2026 \u201d\u6ca1\u529e\u6cd5\u4e0d\u559c\u6b22\u8fd9\u6837\u7684\u5f71\u7247\uff0c\u8bbe\u5b9a\u6709\u8da3\uff0c\u5e7d\u9ed8\u65e0\u5904\u4e0d\u5728\uff0c\u5404\u79cd\u51b7\u5632\u70ed\u8bbd\uff0c\u4f46\u6216\u8bb8\u662f\u6211\u7b11\u70b9\u592a\u9ad8\u7684\u7f18\u6545\uff0c\u59cb\u7ec8\u6ca1\u6709\u611f\u53d7\u5230\u5176\u4ed6\u4eba\u90a3\u79cd\u6216\u5fcd\u4fca\u4e0d\u7981\u6216\u6367\u8179\u5927\u7b11\u3002\u2605\u2605\u2605\u2605", "created_at": "2011-07-14 11:23:16", "id": "413833410"}, {"rating": {"max": 5, "value": 4.0, "min": 0}, "useful_count": 1, "author": {"uid": "76851962", "avatar": "https://img3.doubanio.com\/icon\/u76851962-10.jpg", "signature": "\u7535\u5f71\u53ef\u4ee5\u8ba9\u4eba\u591a\u6d3b\u4e24\u4e2a\u4eba\u751f", "alt": "https:\/\/www.douban.com\/people\/76851962\/", "id": "76851962", "name": "\u5c0f\u9a6c.\u738b"}, "subject_id": "1303418", "content": "\u60c5\u8282\u590d\u6742\u7684\u620f\u4e2d\u620f\uff0c\u201c\u6025\u667a\u201d\u624d\u662f\u4e00\u4e2a\u4f18\u79c0\u6f14\u5458\u7684\u6700\u9ad8\u4fee\u517b\u3002\u7edd\u5999\u7684\u53f0\u8bcd\uff0c\u8ba9\u4eba\u5728\u5f00\u6000\u5927\u7b11\u7684\u540c\u65f6\uff0c\u4f53\u4f1a\u5230\u4e00\u79cd\u667a\u6167\u3002\u4e0d\u8fc7\u66f2\u6298\u7684\u5267\u60c5\u8fd8\u662f\u7ed9\u5f71\u7247\u5e26\u6765\u4e86\u4e00\u4e9b\u7ec6\u8282\u8868\u8ff0\u4e0a\u7684\u7c97\u7cd9\u3002\u8fd9\u662f\u4e00\u4e2a\u8352\u8bde\u7684\u6545\u4e8b\uff0c\u4f46\u540c\u65f6\u53c8\u6709\u7740\u4e25\u8083\u7684\u7231\u56fd\u4e3b\u9898\u3002\u8003\u8651\u5230\u5f71\u7247\u7684\u4e0a\u6620\u65f6\u95f4\uff0c\u675c\u62c9\u5148\u751f\u7684\u80dc\u5229\u5e94\u8be5\u4e5f\u662f\u5bc4\u6258\u4e86\u5bfc\u6f14\u5bf9\u4e8e\u6b63\u4e49\u7684\u4fe1\u5ff5\u5427\u3002", "created_at": "2017-01-05 20:08:52", "id": "1132557494"}, {"rating": {"max": 5, "value": 5.0, "min": 0}, "useful_count": 0, "author": {"uid": "sosad", "avatar": "https://img3.doubanio.com\/icon\/u30337255-6.jpg", "signature": "\u4eba\u90fd\u662f\u8981\u6b7b\u7684", "alt": "https:\/\/www.douban.com\/people\/sosad\/", "id": "30337255", "name": "\u5982\u6765"}, "subject_id": "1303418", "content": "\u5267\u672c\u6784\u601d\u975e\u5e38\u5de7\u5999\uff0c\u4eba\u7269\u8868\u6f14\u975e\u5e38\u51fa\u8272\uff0c\u65e0\u8bba\u4e3b\u89d2\u914d\u89d2\uff0c\u559c\u5267\u6027\u7684\u5904\u7406\u6218\u4e89\u3001\u95f4\u8c0d\u3001\u7eb3\u7cb9\u5fb7\u56fd\u3001\u5e0c\u7279\u52d2\u672c\u4eba\uff0c\u4e3b\u7ebf\u4e4b\u4e0b\u8fd8\u4e00\u76f4\u8c03\u4f83\u7740\u7537\u5973\u4e3b\u89d2\u7684\u611f\u60c5\u7b11\u6599\u3002\u4e0a\u6620\u7684\u65f6\u5019\u6218\u4e89\u8fd8\u6ca1\u7ed3\u675f\u5462\uff0c\u771f\u662f\u90e8\u6709\u73b0\u5b9e\u610f\u4e49\u7684\u5e7d\u9ed8\u4e25\u8083\u7535\u5f71\u3002", "created_at": "2011-12-15 14:24:56", "id": "436248682"}, {"rating": {"max": 5, "value": 5.0, "min": 0}, "useful_count": 3, "author": {"uid": "pigeye", "avatar": "https://img1.doubanio.com\/icon\/u1264081-8.jpg", "signature": "\u516c\u4f17\u53f7: highgossip", "alt": "https:\/\/www.douban.com\/people\/pigeye\/", "id": "1264081", "name": "\u76ae\u9769\u4e1a"}, "subject_id": "1303418", "content": "What he did to Shakespear, we are now doing to Poland.", "created_at": "2012-04-02 00:51:18", "id": "515279472"}, {"rating": {"max": 5, "value": 5.0, "min": 0}, "useful_count": 0, "author": {"uid": "ayida365", "avatar": "https://img1.doubanio.com\/icon\/u1158627-19.jpg", "signature": "\u90fd\u662f\u5c41\u4e8b", "alt": "https:\/\/www.douban.com\/people\/ayida365\/", "id": "1158627", "name": "\u963f\u4f9d\u8fbe"}, "subject_id": "1303418", "content": "\u4e00\u7fa4\u6f14\u5458\u4e71\u5165\u653f\u754c\uff0c\u6405\u5f97\u5929\u7ffb\u5730\u8986\u9e21\u72ac\u4e0d\u5b81\u3002\u5404\u79cd\u60ca\u9669\u60ac\u7591\u65f6\u523b\uff0c\u7adf\u7136\u8fd8\u90fd\u6b6a\u6253\u6b63\u7740\u5316\u9669\u4e3a\u5937\u3002\u641e\u7b11\u5305\u88b1\u4e00\u4e2a\u63a5\u7740\u4e00\u4e2a\uff0c\u90fd\u6bd4\u8f83subtle\uff0c\u503c\u5f97\u4f53\u5473\uff0c\u7b97\u662f\u6bd4\u8f83clever\u7684\u90a3\u79cd\u3002\u7ed3\u5c3e\u5973\u4e3b\u7684\u4e08\u592b\u3001\u98de\u884c\u5458\u770b\u7740\u53e6\u4e00\u4e2a\u7537\u4eba\u5728\u53f0\u8bcd\u5ff5\u5230\u4e00\u534a\u5c31\u9000\u573a\u65f6\u7684\u76ee\u77aa\u53e3\u5446\u7684\u6837\u5b50\uff0c\u53ef\u662f\u628a\u6211\u770b\u5f97\u4e50\u5f97\u4e0d\u5f97\u4e86\u3002", "created_at": "2013-08-04 03:15:32", "id": "622864715"}, {"rating": {"max": 5, "value": 4.0, "min": 0}, "useful_count": 0, "author": {"uid": "2029664", "avatar": "https://img3.doubanio.com\/icon\/u2029664-4.jpg", "signature": "", "alt": "https:\/\/www.douban.com\/people\/2029664\/", "id": "2029664", "name": "jared"}, "subject_id": "1303418", "content": "to be or not to be\uff0c\u6b63\u5982\u7535\u5f71\u4e2d\u63d0\u5230\u7684\u50cf\u4e00\u4e2a\u4ee3\u7801\u3002\u662f\u4e00\u5207\u559c\u5267\u51b2\u7a81\u5f00\u59cb\u7684\u6807\u5fd7\u3002\u5f53\u7537\u4e3b\u89d2\u5728\u821e\u53f0\u4e0a\u5ff5\u8d77\u8fd9\u53e5\u53f0\u8bcd\uff0c\u610f\u5473\u7740\u4ed6\u7684\u60c5\u654c\u5373\u5c06\u548c\u4ed6\u7684\u59bb\u5b50\u5e7d\u4f1a\u3002\u800c\u5f53\u8fd9\u53e5\u53f0\u8bcd\u4ece\u82f1\u683c\u5170\u4f20\u9012\u5230\u5973\u4e3b\u89d2\u7684\u8033\u6735\uff0c\u4e00\u7fa4\u821e\u53f0\u5267\u6f14\u5458\u51fb\u788e\u7eb3\u7cb9\u9634\u8c0b\u7684\u6ed1\u7a3d\u620f\u5373\u5c06\u4e0a\u6f14\u2026\u2026", "created_at": "2012-02-14 14:14:52", "id": "495690713"}, {"rating": {"max": 5, "value": 5.0, "min": 0}, "useful_count": 0, "author": {"uid": "63612050", "avatar": "https://img3.doubanio.com\/icon\/u63612050-15.jpg", "signature": "", "alt": "https:\/\/www.douban.com\/people\/63612050\/", "id": "63612050", "name": "\u97e9\u666f\u5cf0\u770b\u7535\u5f71"}, "subject_id": "1303418", "content": "\u7535\u5f71\u7684\u6545\u4e8b\u7b80\u6d01\u660e\u4e86\u3001\u5e72\u8106\u5229\u843d\uff0c\u8282\u594f\u7d27\u51d1\u6709\u5e8f\uff0c\u5218\u522b\u8c26\u7684\u7ec6\u8282\u8bbe\u8ba1\u53ef\u4ee5\u8bf4\u5320\u5fc3\u72ec\u8fd0\uff0c\u8bc1\u660e\u6210\u4e3a\u7ecf\u5178\u65e2\u8981\u7b80\u5355\u53c8\u4e0d\u90a3\u4e48\u7b80\u5355\u3002\u5218\u522b\u8c26\u7684\u559c\u5267\u582a\u79f0\u4f1f\u5927\uff0c\u4ed6\u7684\u5e7d\u9ed8\u4e0d\u4f4e\u4fd7\u3001\u4e0d\u523b\u610f\u3001\u6709\u601d\u8003\u3001\u6709\u6545\u4e8b\uff0c\u603b\u662f\u5728\u9971\u542b\u667a\u6167\u7684\u5267\u60c5\u53cd\u8f6c\u548c\u620f\u5267\u51b2\u7a81\u4e2d\u5236\u9020\u559c\u5267\u6548\u679c\uff0c\u800c\u300a\u4f60\u9003\u6211\u4e5f\u9003\u300b\u7684\u786e\u53c8\u662f\u4e2a\u4e2d\u7fd8\u695a\u3002", "created_at": "2014-03-18 13:46:28", "id": "787408589"}, {"rating": {"max": 5, "value": 5.0, "min": 0}, "useful_count": 0, "author": {"uid": "zunchi", "avatar": "https://img3.doubanio.com\/icon\/u3282172-4.jpg", "signature": "", "alt": "https:\/\/www.douban.com\/people\/zunchi\/", "id": "3282172", "name": "\u5c0a\u9a70"}, "subject_id": "1303418", "content": "8.6\u5206  \u7b2c\u4e00\u6b21\u770b\u5218\u522b\u8c26\u7684\u7535\u5f71\u5c31\u6709\u5f88\u597d\u7684\u5370\u8c61\uff0c\u611f\u89c9\u8981\u6bd4\u5353\u522b\u6797\u7684\u90a3\u79cd\u523b\u610f\u8868\u6f14\u7684\u559c\u5267\u6709\u610f\u601d\uff0c\u867d\u7136\u672c\u7247\u4e5f\u523b\u610f\u505a\u4e86\u559c\u5267\u6548\u679c\u4e0d\u8fc7\u8fd8\u662f\u4ee5\u5267\u60c5\u641e\u7b11\u4e3a\u4e3b\u3002\u6700\u540e\u7684\u89c2\u4f17\u8d77\u8eab\u5bd3\u610f\u5f88\u6df1\uff0c\u54c8\u54c8\u3002", "created_at": "2011-06-19 18:00:19", "id": "372475815"}, {"rating": {"max": 5, "value": 5.0, "min": 0}, "useful_count": 0, "author": {"uid": "levitating", "avatar": "https://img1.doubanio.com\/icon\/u1265100-27.jpg", "signature": "\u8fdc\u5c71\u6de1\u5f71 \u6bd4\u6d77\u66f4\u6df1", "alt": "https:\/\/www.douban.com\/people\/levitating\/", "id": "1265100", "name": "levitating"}, "subject_id": "1303418", "content": "\u5f88\u68d2\u7684\u5267\u672c\u67b6\u6784\uff0c\u9664\u4e86\u4fcf\u76ae\u7684\u53f0\u8bcd\uff0c\u6240\u6709\u201c\u620f\u4e2d\u620f\u201d\u90fd\u547c\u5e94\u4e86\u8d77\u6765\uff1a1\u3001to be or not to be\uff1b2\u3001\u6301\u957f\u77db\u7684\u9f99\u5957\u6f14\u5458\uff1b3\u3001\u5e0c\u7279\u52d2\u7684\u6f14\u5458\uff1b4\u3001\u80e1\u5b50\uff1b5\u3001\u675c\u62c9\u5148\u751f\u626e\u6f14\u827e\u54c8\u7279\u548c\u6559\u6388\u7684\u4e24\u573a\u620f\u4e5f\u662f\u76f8\u8f89\u6620\uff1b6\u3001\u5173\u4e8e\u5e0c\u7279\u52d2\u7684\u7b11\u8bdd\u3002", "created_at": "2011-03-06 02:27:24", "id": "355419240"}, {"rating": {"max": 5, "value": 4.0, "min": 0}, "useful_count": 0, "author": {"uid": "SoyQueenaTse", "avatar": "https://img1.doubanio.com\/icon\/u1663814-299.jpg", "signature": "\u4f60\u5728\u6240\u6709\u7684\u7a7a\u9593\u88e1\u76db\u958b\u2026", "alt": "https:\/\/www.douban.com\/people\/SoyQueenaTse\/", "id": "1663814", "name": "Chapelle L."}, "subject_id": "1303418", "content": "to be or not to be that's a question \u5f88\u6709\u8da3 \u5145\u6eff\u667a\u6167\u7684\u7537\u4eba \u9b45\u529b\u7121\u9650\uff01 \u7d50\u5c40\u4e00\u5e55\u96d6\u7136\u731c\u5230\u4e86 \u4f46\u4f9d\u7136\u6703\u5fc3\u4e00\u7b11~", "created_at": "2013-09-14 23:36:51", "id": "723474375"}, {"rating": {"max": 5, "value": 4.0, "min": 0}, "useful_count": 0, "author": {"uid": "CammyWhite", "avatar": "https://img1.doubanio.com\/icon\/u1895572-118.jpg", "signature": "\u4f4e\u7aef\u4e00\u661f\u4eba\u53e3\u2026\u2026", "alt": "https:\/\/www.douban.com\/people\/CammyWhite\/", "id": "1895572", "name": "\u2605\u2606\u2606\u2606\u2606"}, "subject_id": "1303418", "content": "\u5c0f\u65f6\u5019\u6700\u521d\u770b\u8fc7\u7684\u662f\u5f69\u8272\u7248\u7684\uff0c\u5f53\u65f6\u6ca1\u88ab\u7b11\u4e2a\u534a\u6b7b\uff08\u5c24\u5176\u6700\u540e\u201c\u5e0c\u7279\u52d2\u201d\u6389\u5728\u82f1\u56fd\u7684\u90a3\u4e00\u6bb5\uff09\u3002\u5218\u522b\u8c26\u6076\u641e\u8d77\u81ea\u5df1\u7684\u7956\u56fd\u4e5f\u6beb\u4e0d\u7559\u60c5\u554a\u2026\u2026\uff08\u5267\u4e2d\u90a3\u6bb5\u201c\u6211\u4eec\u540c\u6837\u9700\u8981\u5403\u98df\u7269\u2026\u2026\u201d\uff0c\u5e94\u8be5\u662f\u6211\u6700\u65e9\u63a5\u89e6\u5230\u7684\u53cd\u79cd\u65cf\u4e3b\u4e49\u601d\u60f3\u4e86\u3002\uff09", "created_at": "2011-09-06 21:05:18", "id": "433645102"}, {"rating": {"max": 5, "value": 5.0, "min": 0}, "useful_count": 1, "author": {"uid": "xukunbing", "avatar": "https://img3.doubanio.com\/icon\/u2510787-23.jpg", "signature": "Aal Izz Well\u2026\u2026", "alt": "https:\/\/www.douban.com\/people\/xukunbing\/", "id": "2510787", "name": "iceman"}, "subject_id": "1303418", "content": "to be or not to be\u2026\u2026jesus\u2026\u2026", "created_at": "2009-08-17 00:05:22", "id": "149567427"}, {"rating": {"max": 5, "value": 5.0, "min": 0}, "useful_count": 0, "author": {"uid": "fzy1993", "avatar": "https://img3.doubanio.com\/icon\/u49123772-5.jpg", "signature": "\u6709\u4eba\u4e00\u5206\u949f\u91cc\u5c31\u5ea6\u8fc7\u4e86\u4e00\u751f\u3002", "alt": "https:\/\/www.douban.com\/people\/fzy1993\/", "id": "49123772", "name": "Anday"}, "subject_id": "1303418", "content": "\u7cbe\u5f69\u7684\u5267\u60c5\uff0c\u6218\u4e89\u7684\u8bbd\u523a\uff0c\u8ba9\u4eba\u55b7\u996d\u7684\u7b11\u70b9\u3001\u53f0\u8bcd\uff0c\u5927\u5e08\u5218\u522b\u8c26\u7684\u6307\u5bfc\uff0c\u8fd9\u662f\u4f60\u4e00\u751f\u4e2d\u4e0d\u53ef\u4e0d\u770b\u7684\u7535\u5f71\u3002\u526f\u4f5c\u7528\u662f\u4eca\u540e\u5f53\u4f60\u542c\u5230\uff1a\u201c\u662f\u751f\u5b58\u8fd8\u662f\u6bc1\u706d\u201d\u8fd9\u53e5\u7ecf\u5178\u53f0\u8bcd\u65f6\uff0c\u4f1a\u7206\u7b11\u3002", "created_at": "2011-06-05 21:06:36", "id": "399474854"}, {"rating": {"max": 5, "value": 5.0, "min": 0}, "useful_count": 0, "author": {"uid": "oojooo", "avatar": "https://img1.doubanio.com\/icon\/u4274697-58.jpg", "signature": "", "alt": "https:\/\/www.douban.com\/people\/oojooo\/", "id": "4274697", "name": "jo"}, "subject_id": "1303418", "content": "totally lubitsch's top three!\u5927\u5e08\u7684\u8fc7\u4eba\u4e4b\u5904\u5c31\u662f\u5e7d\u9ed8\u5730\u6070\u5230\u597d\u5904\u800c\u4e14\u8ba9\u4f60\u5fc3\u670d\u53e3\u670d\uff0c\u8bbd\u523a\u6316\u82e6\u672c\u6765\u5c31\u4e0d\u9700\u8981\u653f\u6cbb\u7acb\u573a\uff0c\u8fde\u8fd9\u70b9prank\u90fd\u63a5\u53d7\u4e0d\u4e86\uff0c\u5b9e\u5728\u592a\u6ca1\u98ce\u5ea6\u4e86", "created_at": "2012-06-25 00:07:51", "id": "548238724"}, {"rating": {"max": 5, "value": 5.0, "min": 0}, "useful_count": 1, "author": {"uid": "lumingtao", "avatar": "https://img3.doubanio.com\/icon\/u1612795-3.jpg", "signature": "\u613f\u773c\u4e2d\u603b\u6709\u5149\u8292\u2502\u6d3b\u6210\u60f3\u8981\u7684\u6a21\u6837", "alt": "https:\/\/www.douban.com\/people\/lumingtao\/", "id": "1612795", "name": "\u9ea6\u515c"}, "subject_id": "1303418", "content": "\u559c\u6b22\u7528\u201c\u5de7\u5999\u201d\u6765\u5f62\u5bb9\u6211\u773c\u4e2d\u7684\u597d\u7535\u5f71\uff0c\u800c\u8fd9\u4e2a\u8bcd\u52a0\u8bf8\u672c\u7247\u7684\u8eab\u4e0a\uff0c\u7adf\u4e5f\u663e\u5f97\u82cd\u767d\u3002\u5982\u6b64\u5730\u60c5\u8da3\u76ce\u7136\u3001\u6d41\u7545\u81ea\u5982\u3001\u81ea\u6210\u4e00\u4f53\uff0c\u5145\u6ee1\u4e86\u8da3\u5473\u548c\u5632\u8bbd\uff0c\u6c14\u8d28\u5353\u7136\u72ec\u7acb\uff0c\u6069\u65af\u7279\u00b7\u5218\u522b\u8c26\u57281942\u5e74\u5df2\u7ecf\u505a\u5230\u4e86\u3002", "created_at": "2014-03-03 17:11:26", "id": "782531301"}, {"rating": {"max": 5, "value": 5.0, "min": 0}, "useful_count": 0, "author": {"uid": "skyto77", "avatar": "https://img3.doubanio.com\/icon\/u1799889-12.jpg", "signature": "\u4e0d\u4ea6\u5feb\u54c9\uff01", "alt": "https:\/\/www.douban.com\/people\/skyto77\/", "id": "1799889", "name": "\u5c0f\u4e59"}, "subject_id": "1303418", "content": "\u559c\u5267\u7684\u529b\u91cf\uff01\u53cd\u6218\u559c\u5267\uff0c\u5218\u522b\u8c26\u7b2c\u4e00\u90e8\uff0c\u60f3\u8d77\u864e\u53e3\u8131\u9669\u3002\u5bf9\u767d\u592a\u592a\u592a\u5389\u5bb3\u4e86\uff0c\u4e3b\u89d2\u51fa\u5f69\uff0c\u914d\u89d2\uff08\u590f\u6d1b\u7279\u7684\u72ec\u767d\uff01\u559c\u5267\u4e2d\u7684\u60b2\u5267\u611f\uff01\uff09\u4e5f\u62a2\u773c\u3002\u653f\u6cbb\u9634\u8c0b\uff0c\u7537\u5973\u5173\u7cfb\uff0c\u5c0f\u4eba\u7269\u83b7\u80dc\uff0c\u559c\u5267\u5e38\u7528\u56e0\u7d20\u5730\u5b8c\u7f8e\u638c\u63a7~\u201c\u4e00\u4e2a\u6f14\u5458\u6700\u5bb3\u6015\u7684\u4e8b\u53d1\u751f\u4e86\uff0c\u6709\u4eba\u5728\u4ed6\u6f14\u51fa\u65f6\u79bb\u573a\u201d\uff08\u7981\u6b62\u8054\u60f3\uff01\u54c8\u54c8\uff09to be...or...not to be\uff01\u4e09\u91cd\u594f~\u54c8\u54c8", "created_at": "2011-09-30 21:36:47", "id": "413835707"}, {"rating": {"max": 5, "value": 5.0, "min": 0}, "useful_count": 0, "author": {"uid": "difeijing", "avatar": "https://img3.doubanio.com\/icon\/u1173975-23.jpg", "signature": "", "alt": "https:\/\/www.douban.com\/people\/difeijing\/", "id": "1173975", "name": "\u72c4\u98de\u60ca"}, "subject_id": "1303418", "content": "\u5c24\u4e3a\u96be\u5f97\u7684\u662f\u5f71\u7247\u6210\u4e8e\u4e8c\u6218\u5c1a\u672a\u53d6\u5f97\u80dc\u5229\u76841942\u5e74\uff0c\u5218\u522b\u8c26\u8fd9\u4efd\u82e6\u4e2d\u4f5c\u4e50\u7684\u7535\u5f71\u60c5\u6000\uff0c\u6ca1\u6709\u5982\u540e\u6765\u7684\u300a\u65e0\u803b\u6df7\u86cb\u300b\u4e00\u822c\u6539\u53d8\u5386\u53f2\uff0c\u5374\u8d85\u8d85\u4e86\u5386\u53f2\u3002", "created_at": "2011-09-03 17:36:18", "id": "431487356"}, {"rating": {"max": 5, "value": 5.0, "min": 0}, "useful_count": 2, "author": {"uid": "colinpark", "avatar": "https://img3.doubanio.com\/icon\/u49097402-173.jpg", "signature": "The Great Clown Pagliacci", "alt": "https:\/\/www.douban.com\/people\/colinpark\/", "id": "49097402", "name": "\u897f\u5e15\u514b"}, "subject_id": "1303418", "content": "CC 2K\u7248\uff0c\u7b2c\u4e09\u6b21\u770b\uff0c\u4f9d\u7136\u4ece\u5934\u7206\u7b11\u5230\u5c3e\uff0c\u53d1\u73b0\u300a\u6bd2\u6218\u300b\u91cc\u4e24\u6b21\u5047\u626e\u8eab\u4efd\u53c2\u52a0\u6bd2\u54c1\u4ea4\u6613\u7684\u6bb5\u843d\uff0c\u5f88\u53ef\u80fd\u5c31\u6a21\u4eff\u81ea\u8fd9\u91cc\u3002", "created_at": "2013-10-02 20:41:03", "id": "731636984"}, {"rating": {"max": 5, "value": 5.0, "min": 0}, "useful_count": 0, "author": {"uid": "ishra", "avatar": "https://img3.doubanio.com\/icon\/u52028582-30.jpg", "signature": "Fear keeps us alive.", "alt": "https:\/\/www.douban.com\/people\/ishra\/", "id": "52028582", "name": "Seddie"}, "subject_id": "1303418", "content": "\u60c5\u8282\u8dcc\u5b95\u8d77\u4f0f\uff0c\u5404\u79cd\u5947\u601d\u5999\u60f3\u3002\u4e00\u4e2a\u4f1f\u5927\u7684\u559c\u5267\u6f14\u5458\uff0c\u8981\u9996\u5148\u61c2\u5f97\u6109\u60a6\u81ea\u5df1\uff0c\u65b9\u53ef\u53d6\u60a6\u4ed6\u4eba\u3002", "created_at": "2012-04-23 18:02:07", "id": "523748533"}, {"rating": {"max": 5, "value": 5.0, "min": 0}, "useful_count": 0, "author": {"uid": "1413100", "avatar": "https://img3.doubanio.com\/icon\/u1413100-14.jpg", "signature": "\u5f15\u8fdb\u843d\u7a7a\u5408\u5373\u51fa", "alt": "https:\/\/www.douban.com\/people\/1413100\/", "id": "1413100", "name": "\u6587\u68ee\u7279"}, "subject_id": "1303418", "content": "\u5c82\u6b62\u662f\u5b8c\u7f8e\uff0c\u7b80\u76f4\u5c31\u662f\u5b8c\u7f8e\uff01\r\n\r\n\u5982\u5353\u522b\u6797\u6240\u8a00\uff0c\u5e84\u4e25\u7684\u80cc\u540e\u5c31\u662f\u8bd9\u8c10\uff0c\u4ed6\u4eec\u662f\u786c\u5e01\u7684\u4e24\u9762\u3002\r\n\r\n\u5218\u522b\u8c26\uff0c\u624d\u534e\u6a2a\u6ea2\uff0c\u7cbe\u5f69\u7edd\u4f26\uff01\r\n\r\n", "created_at": "2011-01-18 01:08:47", "id": "338761076"}, {"rating": {"max": 5, "value": 5.0, "min": 0}, "useful_count": 3, "author": {"uid": "nezhaboy", "avatar": "https://img3.doubanio.com\/icon\/u42174843-51.jpg", "signature": "\u4f1f\u5927\u7684\u53d1\u660e\u8fd8\u5728\u540e\u5934", "alt": "https:\/\/www.douban.com\/people\/nezhaboy\/", "id": "42174843", "name": "\u54ea\u5412\u7537"}, "subject_id": "1303418", "content": "\u6551\u56fd\u5267\u56e2\u3002\u53f0\u6e7e\u53cd\u653b\u5927\u9646\u7684\u8bdd\uff0c\u7116\u9505\u7684\u6a21\u4eff\u8d85\u4eba\u4eec\u4e00\u5b9a\u4f1a\u7acb\u4e0b\u8d6b\u8d6b\u6218\u529f\u3002", "created_at": "2013-10-08 20:36:31", "id": "733688631"}, {"rating": {"max": 5, "value": 5.0, "min": 0}, "useful_count": 1, "author": {"uid": "terenceyibo", "avatar": "https://img1.doubanio.com\/icon\/u80915199-7.jpg", "signature": "I'm Dougie's Coffee.", "alt": "https:\/\/www.douban.com\/people\/terenceyibo\/", "id": "80915199", "name": "Terence_W_Yang"}, "subject_id": "1303418", "content": "\u672c\u7247\u4e4b\u5e7d\u9ed8\u98ce\u8da3\u5b9e\u5728\u662f\u8ba9\u4eba\u5fcd\u4fca\u4e0d\u7981\uff0c\u800c\u5176\u8868\u73b0\u65b9\u5f0f\u53c8\u5b9e\u5728\u4ee4\u4eba\u9707\u60ca\uff0c\u5176\u5267\u4f5c\u5b9e\u5728\u662f\u592a\u6709\u60f3\u8c61\u529b\u4e86\uff0c\u5728\u73af\u73af\u76f8\u6263\u7684\u9017\u8da3\u60c5\u8282\u3001\u76ee\u4e0d\u6687\u63a5\u7684\u89d2\u8272\u53d8\u5316\u548c\u620f\u4e2d\u620f\u7684\u4e0d\u65ad\u8f6c\u6362\u4e2d\uff0c\u540c\u65f6\u5b8c\u6210\u4e86\u5176\u5a31\u4e50\u610f\u4e49\u548c\u73b0\u5b9e\u610f\u4e49\uff0c\u592a\u68d2\u4e86\u3002", "created_at": "2016-02-07 17:58:25", "id": "909687460"}, {"rating": {"max": 5, "value": 5.0, "min": 0}, "useful_count": 0, "author": {"uid": "3403686", "avatar": "https://img1.doubanio.com\/icon\/u3403686-9.jpg", "signature": "\u6211\u662f\u602a\u5496\u6211\u6015who", "alt": "https:\/\/www.douban.com\/people\/3403686\/", "id": "3403686", "name": "\u8d85cute\u4fa0"}, "subject_id": "1303418", "content": "\u6545\u4e8b\u5938\u5f20\u800c\u641e\u7b11\uff0c\u7ed3\u6784\u7cbe\u5de7\u800c\u7ec6\u81f4\uff0c\u5218\u522b\u8c26\u7684\u559c\u5267\u5f88\u6709\u667a\u6167\u3002", "created_at": "2012-12-25 16:03:35", "id": "620687422"}, {"rating": {"max": 5, "value": 5.0, "min": 0}, "useful_count": 0, "author": {"uid": "dusk.xiyang", "avatar": "https://img3.doubanio.com\/icon\/u4581247-80.jpg", "signature": "\u65b0\u9c9c\u5783\u573e", "alt": "https:\/\/www.douban.com\/people\/dusk.xiyang\/", "id": "4581247", "name": "\u96fe\u7559\u5206\u513f"}, "subject_id": "1303418", "content": "#670 2b\u6216\u4e0d2b...\u6700\u540e\u79bb\u573a\u8fd8\u6296\u4e00\u4e0b\u5305\u88b1\uff0c\u7d27\u5f20\u4e2d\u53c8\u65f6\u4e0d\u65f6\u7684\u6233\u4e0b\u4f60\u7b11\u70b9\uff0c\u6362\u8eab\u4efd\u7684\u6897\u539f\u6765\u5218\u522b\u8c26\u65e9\u7528\u4e86\uff0cheil myself!!\u8fd9\u4e9b\u4e8c\u6218\u7684\u559c\u5267\u771f\u9017\uff0c\u864e\u53e3\u8131\u9669\u548c\u65e0\u803b\u6df7\u86cb\u770b\u5230\u501f\u9274\u7684\u5f71\u5b50\u3010Lubitsch touch", "created_at": "2013-12-13 15:17:38", "id": "753552786"}, {"rating": {"max": 5, "value": 5.0, "min": 0}, "useful_count": 0, "author": {"uid": "fastkill", "avatar": "https://img1.doubanio.com\/icon\/u4721359-7.jpg", "signature": "\u65e9\u788e\u65e9\u5f03\u5c38\u4f53\u597d\u3002", "alt": "https:\/\/www.douban.com\/people\/fastkill\/", "id": "4721359", "name": "\u66f9\u963f\u7792"}, "subject_id": "1303418", "content": "\u5999\u4e0d\u53ef\u8a00\u7684\u559c\u5267\u7247\u3002\u60c5\u8282\u4e00\u6ce2\u4e09\u6298\uff0c\u65e0\u5904\u4e0d\u5728\u7684\u53cd\u8bbd\uff0c\u53f0\u8bcd\u4e5f\u7cbe\u5f69\u81f3\u6781\u3002", "created_at": "2012-04-09 00:41:48", "id": "518209479"}, {"rating": {"max": 5, "value": 4.0, "min": 0}, "useful_count": 2, "author": {"uid": "pedant", "avatar": "https://img3.doubanio.com\/icon\/u4278255-102.jpg", "signature": "\u541b\u70ba\u5b8b\u671d\u4f50\u547d\uff0c\u543e\u4e43\u6649\u5ba4\u907a\u8001", "alt": "https:\/\/www.douban.com\/people\/pedant\/", "id": "4278255", "name": "\u9b3c\u8173\u4e03"}, "subject_id": "1303418", "content": "\u5218\u522b\u8c26\u6beb\u65e0\u7591\u95ee\u6709\u5929\u624d\uff0c\u800c\u4e14\u8868\u73b0\u5f97\u6dcb\u6f13\u5c3d\u81f4\u3002\u5728\u8ba9\u4eba\u6367\u8179\u548c\u53cd\u601d\u7684\u5c3a\u5ea6\u548c\u8f6c\u6362\u4e0a\u90fd\u628a\u63e1\u5730\u76f8\u5f53\u597d\u3002\u4f46\u662f\u4e5f\u4e0d\u5f97\u4e0d\u8bf4\uff0c\u8fd9\u79cd\u559c\u5267\u5316\u7684\u624b\u6cd5\u663e\u5f97\u8fc7\u4e8e\u4e50\u89c2\u4e86\uff0c\u4e00\u526f\u9694\u5cb8\u89c2\u706b\u7684\u900d\u9065\u6001\u5ea6\u3002", "created_at": "2011-05-08 13:22:03", "id": "387762307"}, {"rating": {"max": 5, "value": 5.0, "min": 0}, "useful_count": 0, "author": {"uid": "kevindreamfly", "avatar": "https://img1.doubanio.com\/icon\/u4318664-98.jpg", "signature": "\u516c\u4f17\u53f7\uff1a\u8700\u841d\u5927\u5192\u9669", "alt": "https:\/\/www.douban.com\/people\/kevindreamfly\/", "id": "4318664", "name": "\u6d6e\u751f\u82e5\u5922"}, "subject_id": "1303418", "content": "\u7cbe\u5de7\u7684\u6784\u601d\uff0c\u72e1\u9ee0\u7684\u5bf9\u767d\u3002\u6545\u4e8b\u6027\u6781\u5f3a\uff0c\u8868\u6f14\u4e5f\u5f88\u7cbe\u5f69\u3002", "created_at": "2011-03-11 15:26:17", "id": "364049817"}, {"rating": {"max": 5, "value": 4.0, "min": 0}, "useful_count": 1, "author": {"uid": "huangye3", "avatar": "https://img3.doubanio.com\/icon\/u40643766-95.jpg", "signature": "\u6700\u6df1\u9083\u7684\u662f\u8868\u5c42", "alt": "https:\/\/www.douban.com\/people\/huangye3\/", "id": "40643766", "name": "\u8352\u4e5f"}, "subject_id": "1303418", "content": "\u4e54\u88c5\u7684\u559c\u5267\u3002\u53cd\u6218\u7684\u559c\u5267\u3002\u5145\u6ee1\u53cc\u5173\u7528\u8bed\u7684\u60c5\u8272\u7b11\u8bdd\u3002\u7528\u4e00\u79cd\u8bbd\u523a\u5e7d\u9ed8\u7684\u65b9\u5f0f\uff0c\u5c06\u592b\u59bb\u77db\u76fe\u5d4c\u5957\u5230\u4e00\u4e2a\u6c89\u91cd\u7684\u5386\u53f2\u73af\u5883\u91cc\u7684\u559c\u5267\u3002\u548c\u4e24\u5e74\u524d\u5353\u522b\u6797\u7684\u300a\u5927\u72ec\u88c1\u8005\u300b\u7684\u7ed3\u5c3e\u4e0d\u540c\u7684\u662f\uff0c\u6700\u540e\u8fd8\u662f\u8fd8\u539f\u5230\u592b\u59bb\u5173\u7cfb\u4e0a\u6765\u3002", "created_at": "2016-11-03 17:48:29", "id": "487912082"}, {"rating": {"max": 5, "value": 5.0, "min": 0}, "useful_count": 0, "author": {"uid": "31249640", "avatar": "https://img3.doubanio.com\/icon\/u31249640-36.jpg", "signature": "", "alt": "https:\/\/www.douban.com\/people\/31249640\/", "id": "31249640", "name": "Fruitpunch"}, "subject_id": "1303418", "content": "\u80fd\u5c06\u4e00\u4e2a\u539f\u672c\u4ee4\u4eba\u611f\u5230\u6050\u60e7\u7684\u7d20\u6750\u62cd\u6210\u559c\u5267\uff0c\u5e76\u4e14\u5f88\u597d\u5730\u5904\u7406\u4e86\u4e25\u8083\u4e0e\u5938\u5927\u4e4b\u95f4\u7684\u5173\u7cfb\uff0c\u4e5f\u53ea\u6709\u5218\u522b\u8c26\u80fd\u505a\u5230\u3002", "created_at": "2012-12-11 00:18:39", "id": "614456694"}, {"rating": {"max": 5, "value": 5.0, "min": 0}, "useful_count": 0, "author": {"uid": "touya0229", "avatar": "https://img3.doubanio.com\/icon\/u46825265-5.jpg", "signature": "\u7535\u5f71\uff0c\u6e56\u4eba\uff0c\u9648\u5955\u8fc5\uff0c\u8759\u8760\u4fa0\u3002", "alt": "https:\/\/www.douban.com\/people\/touya0229\/", "id": "46825265", "name": "touya"}, "subject_id": "1303418", "content": "\u6ca1\u6709\u7206\u7b11\uff0c\u53cd\u5012\u662f\u5c0f\u5e7d\u9ed8\u4e0d\u65ad\uff0c\u770b\u5f97\u4eba\u5f00\u5fc3\u53c8\u5e26\u4e9b\u7d27\u5f20\uff0c\u6bcf\u6b21\u51fa\u73b0\u5371\u9669\u4e4b\u65f6\u90fd\u4f1a\u6709\u521a\u597d\u7684\u65f6\u673a\u53bb\u906e\u76d6\uff0c\u81ea\u604b\u7684\u6f14\u5458\u592b\u5987\u53cd\u5012\u5728\u771f\u5b9e\u7eb3\u7cb9\u524d\u5927\u79c0\u4e86\u628a\u6f14\u6280~\u6700\u4f69\u670d\u7684\u5c31\u662f\u6545\u4e8b\u7684\u8854\u63a5\uff0c\u771f\u662f\u8fde\u63a5\u7684\u7edd\u5999\u3002Carole Lombard\uff0cGable\u6700\u7231\u7684\u5973\u4eba\uff0c\u53c8\u7f8e\u53c8\u53ef\u7231\u53c8\u575a\u6bc5\u3002", "created_at": "2017-11-14 21:22:07", "id": "1271211658"}, {"rating": {"max": 5, "value": 4.0, "min": 0}, "useful_count": 0, "author": {"uid": "angalny", "avatar": "https://img3.doubanio.com\/icon\/u2657343-2.jpg", "signature": "\u6211\u7684\u5e78\u798f\u5f88\u7b80\u5355", "alt": "https:\/\/www.douban.com\/people\/angalny\/", "id": "2657343", "name": "\u738b\u5c0f\u5317"}, "subject_id": "1303418", "content": "\u5f00\u573a\u5f88\u7ecf\u5178\uff0c\u55e8\uff0c\u6211\u81ea\u5df1\uff01\u540e\u6765\uff0c\u5854\u4f26\u8482\u8bfa\u8ba9\u7eb3\u7cb9\u6709\u4e86\u667a\u5546\uff0c\u53ef\u4ee5\u4f9d\u65e7\u53e3\u97f3\u9274\u522b\u51fa\u4f60\u662f\u82f1\u56fd\u4eba\u5047\u626e\u7684\u8fd8\u662f\u6b63\u5b97\u7684\u5fb7\u56fd\u4eba\u3002", "created_at": "2012-08-19 17:38:08", "id": "570146900"}, {"rating": {"max": 5, "value": 4.0, "min": 0}, "useful_count": 0, "author": {"uid": "wanger0619", "avatar": "https://img1.doubanio.com\/icon\/u2056470-37.jpg", "signature": "\u4e0d\u601d\u8b70\u306a\u4e8b\u306a\u3069\u4f55\u3082\u306a\u3044\u306e\u3060\u3088", "alt": "https:\/\/www.douban.com\/people\/wanger0619\/", "id": "2056470", "name": "451\u00bd\u00b0F\u2122"}, "subject_id": "1303418", "content": "http:\/\/www.tudou.com\/programs\/view\/dxWNMG4E_EM\/", "created_at": "2008-12-07 15:57:40", "id": "39074196"}, {"rating": {"max": 5, "value": 4.0, "min": 0}, "useful_count": 0, "author": {"uid": "64011512", "avatar": "https://img1.doubanio.com\/icon\/u64011512-29.jpg", "signature": "", "alt": "https:\/\/www.douban.com\/people\/64011512\/", "id": "64011512", "name": "\u4e8c\u8d27\u4e91"}, "subject_id": "1303418", "content": "\u201dto be or not to be\u201c\uff0f\u8d77\u8eab\u79bb\u5f00\uff0f\u5404\u79cd\u6392\u6bd4\uff0f\u795e\u6f14\u6280\uff0c\u65e0\u53ef\u6311\u5254\u7684\u5b8c\u7f8e\uff0c\u53ea\u56e0\u6ca1\u6709\u653e\u58f0\u5927\u7b11\uff0c\u4e5f\u4e0d\u66fe\u5931\u58f0\u75db\u54ed\uff0c\u6240\u4ee5\u56db\u661f\u3002", "created_at": "2014-02-09 21:59:10", "id": "621602204"}, {"rating": {"max": 5, "value": 5.0, "min": 0}, "useful_count": 0, "author": {"uid": "54621732", "avatar": "https://img3.doubanio.com\/icon\/u54621732-2.jpg", "signature": "", "alt": "https:\/\/www.douban.com\/people\/54621732\/", "id": "54621732", "name": "\u6211\u547c\u5438\u7684\u7a7a\u6c14"}, "subject_id": "1303418", "content": "A superb blend of comedy and drama.  Witty dialogues rule!", "created_at": "2013-01-29 18:35:06", "id": "636470938"}, {"rating": {"max": 5, "value": 5.0, "min": 0}, "useful_count": 0, "author": {"uid": "Easy_Rider", "avatar": "https://img1.doubanio.com\/icon\/u43632664-87.jpg", "signature": "Nobody calls me chicken.", "alt": "https:\/\/www.douban.com\/people\/Easy_Rider\/", "id": "43632664", "name": "Marty McFly"}, "subject_id": "1303418", "content": "A Great Masterpiece. \u4e00\u90e8\u7edd\u5999\u7684\u7cbe\u5f69\u559c\u5267\uff01", "created_at": "2011-09-05 20:20:14", "id": "433333426"}, {"rating": {"max": 5, "value": 5.0, "min": 0}, "useful_count": 0, "author": {"uid": "53869175", "avatar": "https://img1.doubanio.com\/icon\/u53869175-57.jpg", "signature": "", "alt": "https:\/\/www.douban.com\/people\/53869175\/", "id": "53869175", "name": "\u5999\u53ef\u4e2d\u56fd"}, "subject_id": "1303418", "content": "\u5b8c\u7f8e\u7684\u8bbd\u523a\u559c\u5267\uff0c\u5218\u522b\u8c26\u5f88\u597d\u7684\u5c06\u79cd\u79cd\u5de7\u5408\u7cc5\u5408\u8d77\u6765\uff0c\u8fd0\u7528\u5230\u6781\u81f4\u3002\u6bcf\u4e2a\u9c9c\u6d3b\u751f\u52a8\u7684\u89d2\u8272\u90fd\u72e1\u733e\u7684\u53ef\u7231\uff0c\u5c24\u5176\u662f\u5fb7\u519b\u4e0a\u6821\u548c\u7537\u4e3b\u89d2\u7684\u4e24\u573a\u5bf9\u624b\u620f\uff0c\u7b11\u5f97\u80c3\u75bc\u3002\u7ed3\u5c3e\u6697\u8bbd\u7eb3\u7cb9\u662f\u65e0\u8111\u6740\u4eba\u673a\u5668\uff0c\u7ecf\u5178\uff01", "created_at": "2016-01-06 14:33:08", "id": "996523444"}, {"rating": {"max": 5, "value": 5.0, "min": 0}, "useful_count": 0, "author": {"uid": "yikepingguo", "avatar": "https://img3.doubanio.com\/icon\/u25170280-2.jpg", "signature": "", "alt": "https:\/\/www.douban.com\/people\/yikepingguo\/", "id": "25170280", "name": "\u4e00\u9897\u82f9\u679c"}, "subject_id": "1303418", "content": "2B or not 2B\uff0c\u90a3\u662f\u4e00\u51fa\u559c\u5267\uff011942\u5e74\u5927\u72ec\u88c1\u8005\u90a3\u4e48\u56a3\u7684\u65f6\u5019\uff0c\u4f60\u4eec\u5c45\u7136\u62cd\u4e2a\u7535\u5f71\u6765\u660e\u53cd\u4ed6\uff0c\u800c\u4e14\u5267\u60c5\u8fd8\u90a3\u4e48\u6709\u610f\u601d\uff01ohohohohoho~good job!    \u6807\u7b7e\uff1a\u7ecf\u5178", "created_at": "2012-03-28 10:21:18", "id": "513485586"}, {"rating": {"max": 5, "value": 5.0, "min": 0}, "useful_count": 0, "author": {"uid": "Innerplant", "avatar": "https://img3.doubanio.com\/icon\/u1919368-102.jpg", "signature": "", "alt": "https:\/\/www.douban.com\/people\/Innerplant\/", "id": "1919368", "name": "\u51ac\u81f3"}, "subject_id": "1303418", "content": "to be or not to be\uff1b\u7b2c\u4e8c\u6b21\u89c2\u770b2012\u00b72\u00b76", "created_at": "2011-04-12 23:52:25", "id": "196905249"}, {"rating": {"max": 5, "value": 4.0, "min": 0}, "useful_count": 0, "author": {"uid": "69290051", "avatar": "https://img3.doubanio.com\/icon\/u69290051-126.jpg", "signature": "\u4e0d\u53ea\u662f\u5f71\u8ff7", "alt": "https:\/\/www.douban.com\/people\/69290051\/", "id": "69290051", "name": "Paco"}, "subject_id": "1303418", "content": "\u7b2c\u4e00\u90e8\u5218\u522b\u8c26\u30021.\u5728\u8bc4\u8bba\u533a\u611f\u53d7\u5230\u6df1\u5165\u9aa8\u9ad3\u7684\u5b64\u72ec\uff1a\u6211\u6015\u662f\u5168\u4e16\u754c\u552f\u4e00\u4e00\u4e2a\u770b\u61c2\u5374\u5168\u7a0b\u6ca1\u7206\u7b11\u8fc7\u7684\u4eba\u4e86...2.\u4f5c\u4e3a\u6211\u63a5\u89e6\u7684\u7b2c\u4e09\u4f4d\u65e9\u671f\u559c\u5267\u5927\u5e08\uff0c\u5218\u4e0e\u5353\u57fa\u4e4b\u6d41\u5dee\u5f02\u660e\u663e\u3002\u5bf9\u6bd4\u540c\u4e3a\u6709\u58f0\/\u4e8c\u6218\u7684\u300a\u5927\u72ec\u88c1\u8005\u300b\uff0c\u4ecd\u53ef\u89c1\u4e24\u8005\u5728\u8bed\u8a00\u4e0e\u80a2\u4f53\u6027\u5e7d\u9ed8\u7684\u503e\u5411\u5206\u522b\uff0c\u4f46\u620f\u5267\u5171\u901a\u30023.\u672c\u7247\u7cbe\u795e\u7eed\u96c6\uff1a\u300a\u65e0\u803b\u6df7\u86cb\u300b\u3002", "created_at": "2018-03-03 05:33:17", "id": "1334640142"}, {"rating": {"max": 5, "value": 5.0, "min": 0}, "useful_count": 0, "author": {"uid": "infero", "avatar": "https://img1.doubanio.com\/icon\/u3490094-87.jpg", "signature": "", "alt": "https:\/\/www.douban.com\/people\/infero\/", "id": "3490094", "name": "infero"}, "subject_id": "1303418", "content": "\"A laugh is nothing to be sneezed at!\"", "created_at": "2010-11-11 11:20:09", "id": "313969786"}, {"rating": {"max": 5, "value": 5.0, "min": 0}, "useful_count": 0, "author": {"uid": "klimax", "avatar": "https://img3.doubanio.com\/icon\/u55951685-242.jpg", "signature": "", "alt": "https:\/\/www.douban.com\/people\/klimax\/", "id": "55951685", "name": "\u739b\u4e3d\u83b2\u00b7\u5b5f\u83b7"}, "subject_id": "1303418", "content": "First it was Hess, now him...", "created_at": "2013-12-18 23:17:35", "id": "754914535"}, {"rating": {"max": 5, "value": 4.0, "min": 0}, "useful_count": 0, "author": {"uid": "feizhuangzhuang", "avatar": "https://img3.doubanio.com\/icon\/u1802767-4.jpg", "signature": "\u751f\u6d3b\u5728\u65c5\u9014\u4e2d", "alt": "https:\/\/www.douban.com\/people\/feizhuangzhuang\/", "id": "1802767", "name": "\u80a5\u58ee\u58ee"}, "subject_id": "1303418", "content": "\u7f8e\u56fd1942\u5e74\u4e8c\u6218\u65f6\u559c\u5267\uff0c\u662f\u597d\u83b1\u575e\u8457\u540d\u559c\u5267\u5bfc\u6f14\u6069\u65af\u7279\u00b7\u5218\u522b\u8c26\u7684\u7ecf\u5178\u4f5c\u54c1\uff0c\u4e5f\u5e94\u8be5\u662f\u5973\u4e3b\u89d2\u5361\u6d1b\u5c14\u00b7\u9686\u5df4\u5fb7\uff0c\u8fd9\u4e2a\u514b\u62c9\u514b.\u76d6\u535a\u6700\u7231\u7684\u5973\u4eba\u51fa\u6f14\u7684\u6700\u540e\u4e00\u90e8\u5f71\u7247\uff0c\u62cd\u5b8c\u540e\u5979\u6b7b\u4e8e\u4e3a\u63a8\u9500\u6218\u4e89\u516c\u503a\u65c5\u884c\u65f6\u7684\u98de\u673a\u5931\u4e8b\u3002\u6b7b\u540e\u76d6\u535a\u4e3a\u597942\u5c81\u8fd8\u53bb\u53c2\u519b\uff0c\u62c5\u4efb\u8f70\u70b8\u673a\u70ae\u624b\uff0c\u4e86\u7ed3\u5979\u7684\u610f\u613f\u3002", "created_at": "2014-04-19 15:27:19", "id": "798364809"}, {"rating": {"max": 5, "value": 5.0, "min": 0}, "useful_count": 0, "author": {"uid": "plumcarp", "avatar": "https://img3.doubanio.com\/icon\/u1018485-5.jpg", "signature": "", "alt": "https:\/\/www.douban.com\/people\/plumcarp\/", "id": "1018485", "name": "\u674e\u5b50\u9ca4|Lilith"}, "subject_id": "1303418", "content": "\u6211\u7ec8\u4e8e\u77e5\u9053\u4e3a\u4ec0\u4e48\u53eb to be or not to be\uff0c\u77e5\u9053\u4e3a\u4ec0\u4e48\u53eb\u300a\u4f60\u9003\u6211\u4e5f\u9003\u300b\uff0c\u4e3a\u4ec0\u4e48\u53eb\u300a\u55e8\uff0c\u6211\u7684\u5143\u9996\u300b\u3002\u4ed6\u600e\u4e48\u80fd\u505a\u5230\u5728\u90a3\u6837\u5c01\u53e3\u6d6a\u5c16\u7684\u5173\u5934\uff0c\u8fd8\u4e0d\u5fd8\u4e89\u98ce\u5403\u918b\u3002\u4ed6\u600e\u4e48\u80fd\u628a\u6218\u4e89\u548c\u559c\u5267\u7528\u4e00\u79cd\u975e\u6ed1\u7a3d\uff08\u80a2\u4f53\u559c\u5267\uff09\u7684\u5f62\u5f0f\u8fd9\u6837\u5b8c\u7f8e\u7684\u7ed3\u5408\u8d77\u6765\uff1f\u4ed6\u600e\u4e48\u80fd\u628a\u6545\u4e8b\u8bb2\u7684\u5982\u6b64\u5438\u5f15\u4eba\uff1f\u4ed6\u7684\u53f0\u8bcd\uff0c\u4ed6\u7684\u6545\u4e8b\uff0c\u548c\u4ed6\u7684\u838e\u58eb\u6bd4\u4e9a\uff0c\u600e\u4e48\u80fd\u4e92\u6587\u7684\u5982\u6b64\u7cbe\u81f4\u800c\u6070\u5230\u597d\u5904\uff1f\u8fd9\u662f\u4e00\u95e8\u5df2\u7136\u5931\u4f20\u7684\u624b\u827a\uff01If you prick us \uff0cdo we not bleed? If you tickle us \uff0cdo we not laugh? If you po", "created_at": "2009-07-16 22:16:47", "id": "139592455"}, {"rating": {"max": 5, "value": 0, "min": 0}, "useful_count": 0, "author": {"uid": "sophielikeit", "avatar": "https://img3.doubanio.com\/icon\/u2672561-96.jpg", "signature": "", "alt": "https:\/\/www.douban.com\/people\/sophielikeit\/", "id": "2672561", "name": "Sophie"}, "subject_id": "1303418", "content": "If you prick us, do we not bleed? If you tickle us, do we not laugh? If you poison us, do we not die? If you wrong us, shall we not revenge?", "created_at": "2011-01-22 20:52:19", "id": "343733355"}, {"rating": {"max": 5, "value": 4.0, "min": 0}, "useful_count": 1, "author": {"uid": "oldwhom", "avatar": "https://img3.doubanio.com\/icon\/u3578803-11.jpg", "signature": "Asche zu Asche Staub zu Staub", "alt": "https:\/\/www.douban.com\/people\/oldwhom\/", "id": "3578803", "name": "Memento Mori"}, "subject_id": "1303418", "content": "\u6211\u53d1\u89c9\uff0c\u5218\u522b\u8c26\u662f\u7535\u5f71\u4eba\u4e2d\u7ffb\u8bd1\u7684\u6700\u597d\u542c\u7684\u3002", "created_at": "2011-05-18 10:45:27", "id": "391806077"}, {"rating": {"max": 5, "value": 5.0, "min": 0}, "useful_count": 0, "author": {"uid": "sai27", "avatar": "https://img3.doubanio.com\/icon\/u4395275-12.jpg", "signature": "", "alt": "https:\/\/www.douban.com\/people\/sai27\/", "id": "4395275", "name": "D"}, "subject_id": "1303418", "content": "If you prick us do we not bleed? If you tickle us do we not laugh? If you poison us do we not die? And if you wrong us shall we not revenge?", "created_at": "2014-05-12 10:44:44", "id": "803843464"}, {"rating": {"max": 5, "value": 5.0, "min": 0}, "useful_count": 1, "author": {"uid": "williampitt", "avatar": "https://img1.doubanio.com\/icon\/u14356307-209.jpg", "signature": "S'il pla\u00eet \u00e0 dieu.", "alt": "https:\/\/www.douban.com\/people\/williampitt\/", "id": "14356307", "name": "Favillae"}, "subject_id": "1303418", "content": "\u6df1\u66f4\u534a\u591c\u7b11\u6210\u6df1\u4e95\u51b0\uff0c\u89c9\u5f97\u6700\u597d\u7b11\u7684\u4e24\u4e2a\u7b11\u70b9\u8fd8\u662f\u5192\u724c\u5143\u9996\u53eb\u90a3\u4fe9\u98de\u884c\u5458jump\u65f6\u4eba\u5bb6\u6beb\u4e0d\u72b9\u8c6b\u5730\u8df3\u673a\u4e86\u3002\u3002\u8fd8\u6709\u7ed3\u5c3e\u63d0\u5fc3\u540a\u80c6\u5ff5\u51fato be or not to be\u65f6\u60c5\u654c\u6ca1\u79bb\u5e2d\u5374\u6362\u522b\u4eba\u79bb\u5e2d\u3002\u3002\u4e2d\u95f4\u201c\u4ed6\u662f\u6208\u6797\u7684\u59d0\u592b\u201d\u3001\u201c\u6700\u521d\u662f\u8d6b\u65af\uff0c\u73b0\u5728\u662f\u4ed6\u201d\u90fd\u4e0d\u7b97\u5565\u4e86\u3002\u3002", "created_at": "2017-06-21 03:05:03", "id": "1205277007"}, {"rating": {"max": 5, "value": 4.0, "min": 0}, "useful_count": 0, "author": {"uid": "46389146", "avatar": "https://img3.doubanio.com\/icon\/u46389146-2.jpg", "signature": "", "alt": "https:\/\/www.douban.com\/people\/46389146\/", "id": "46389146", "name": "probe"}, "subject_id": "1303418", "content": "\u8001\u5e08\u6559\u80b2\u6211\u4eec\u522b\u6492\u8c0e\uff0c\u8c0e\u8bdd\u4f1a\u8d8a\u8bf4\u8d8a\u591a\uff0c\u8d8a\u8bf4\u8d8a\u5927\u3002\u53ef\u8c0e\u8bdd\u8d8a\u591a\u8d8a\u5927\u5c31\u80fd\u6210\u4e00\u90e8\u7535\u5f71\u54c8\uff01\u4e0d\u4f46\u662f\u620f\u4e2d\u620f\u8fde\u73af\u5957\uff0c\u628a\u4e09\u89d2\u604b\u7684\u641e\u7b11\u4e0e\u8c0d\u6218\u7684\u7d27\u5f20\u611f\u5de7\u5999\u7684\u7f16\u7ec7\u5728\u4e00\u8d77\uff0c\u5404\u79cd\u903b\u8f91\u4e0d\u5408\u8352\u8bde\u4e0d\u7ecf\u4e4b\u5904\u6b63\u597d\u90fd\u88ab\u5229\u7528\u4f5c\u4e3a\u5bf9\u7eb3\u7cb9\u7684\u8bbd\u523a\u4e0e\u5bf9\u620f\u5267\u7684\u5d07\u656c\uff0c\u903b\u8f91\u4e5f\u5f97\u8ba9\u4f4d\u4e8e\u7206\u68da\u7684\u53cd\u8f6c\u60f3\u8c61\u529b\u3002\u6700\u540e\u5267\u9662\u9003\u8131\u7f16\u7684\u6f0f\u6d1e\u591a\u5230\u5931\u63a7\u6bd4\u8f83\u7455\u75b5", "created_at": "2017-12-01 11:47:15", "id": "1279233009"}, {"rating": {"max": 5, "value": 4.0, "min": 0}, "useful_count": 0, "author": {"uid": "wangdong1120", "avatar": "https://img3.doubanio.com\/icon\/u1458339-55.jpg", "signature": "", "alt": "https:\/\/www.douban.com\/people\/wangdong1120\/", "id": "1458339", "name": "Bill"}, "subject_id": "1303418", "content": "\u975e\u5e38\u6709\u610f\u601d\u7684\u4e00\u90e8\u7247\u5b50 \u60c5\u8282\u5999\u4e0d\u53ef\u8a00 \u5218\u522b\u8c26", "created_at": "2008-12-13 00:49:10", "id": "79297149"}, {"rating": {"max": 5, "value": 5.0, "min": 0}, "useful_count": 1, "author": {"uid": "49343894", "avatar": "https://img3.doubanio.com\/icon\/u49343894-16.jpg", "signature": "", "alt": "https:\/\/www.douban.com\/people\/49343894\/", "id": "49343894", "name": "\u5317\u65b9\u7684\u6cb3"}, "subject_id": "1303418", "content": "\u53f0\u8bcd\u7684\u7b80\u5355\u91cd\u590d\uff0c\u7adf\u80fd\u4ea7\u751f\u5982\u6b64\u53eb\u7edd\u7684\u6548\u679c\uff01\u300a\u5927\u8bdd\u897f\u6e38\u300b\u4e2d\u90a3\u53e5\u201c\u66fe\u7ecf\u6709\u4e00\u6bb5\u7231\u653e\u5728\u6211\u7684\u9762\u524d\u2026\u2026\u201d\u5e94\u8be5\u65e0\u4eba\u80fd\u591f\u5fd8\u8bb0\u3002\u540c\u6837\u7684\uff0c\u672c\u7247\u591a\u6b21\u573a\u666f\u4e2d\uff0c\u540c\u6837\u7684\u53f0\u8bcd\u91cd\u590d\u51fa\u73b0\uff0c\u6bcf\u4e00\u6b21\u8574\u542b\u4e0d\u540c\u7684\u610f\u601d\uff0c\u4ee4\u4eba\u6367\u8179\u3002\u5982\u679c\u5728\u89c2\u5f71\u4f60\u8bfb\u8fc7\u300a\u54c8\u59c6\u96f7\u7279\u300b\u548c\u300a\u5a01\u5c3c\u65af\u5546\u4eba\u300b\uff0c\u4e50\u8da3\u65e0\u7591\u4f1a\u500d\u589e\u2014\u2014\u597d\u591a\u53f0\u8bcd\u76f4\u63a5\u53d6\u81ea\u8fd9\u4e24\u90e8\u620f\u5267\u3002", "created_at": "2012-11-14 23:00:22", "id": "602542235"}, {"rating": {"max": 5, "value": 5.0, "min": 0}, "useful_count": 1, "author": {"uid": "shoegazerbaby", "avatar": "https://img3.doubanio.com\/icon\/u3823154-460.jpg", "signature": "_(\u25bc_\u25bc\u300d\u2220)_\u8c46\u74e3\u8001\u5e74\u4eba", "alt": "https:\/\/www.douban.com\/people\/shoegazerbaby\/", "id": "3823154", "name": "shoegazerbaby"}, "subject_id": "1303418", "content": "1942\u5e74\u7684\u4e5f\u80fd\u628a\u6211\u4eec\u4e00\u5bb6\u90fd\u4e50\u574f\u4e86~ \u4f1f\u5927\u7684\u559c\u5267\uff01", "created_at": "2010-12-01 15:25:27", "id": "321337465"}, {"rating": {"max": 5, "value": 5.0, "min": 0}, "useful_count": 1, "author": {"uid": "138576790", "avatar": "https://img3.doubanio.com\/icon\/u138576790-2.jpg", "signature": "", "alt": "https:\/\/www.douban.com\/people\/138576790\/", "id": "138576790", "name": "\u6211\u5feb\u4e50\u6211\u5e78\u798f"}, "subject_id": "1303418", "content": "\u597d\u7535\u5f71\u53ef\u4ee5\u6ca1\u6709\u7279\u6280\uff0c\u6ca1\u6709\u7206\u7834\uff0c\u6ca1\u6709\u5927\u573a\u9762\uff0c\u6ca1\u6709\u7231\u60c5\uff0c\u6ca1\u6709\u7f8e\u5973\uff0c\u53ea\u8981\u6709\u597d\u5267\u672c\u548c\u597d\u6f14\u5458\u8db3\u77e3\u3002", "created_at": "2016-04-10 16:30:20", "id": "1030330901"}, {"rating": {"max": 5, "value": 0, "min": 0}, "useful_count": 0, "author": {"uid": "2352053", "avatar": "https://img3.doubanio.com\/icon\/u2352053-324.jpg", "signature": "", "alt": "https:\/\/www.douban.com\/people\/2352053\/", "id": "2352053", "name": "Grippe"}, "subject_id": "1303418", "content": "to be or not to be\u7684\u786e\u662f\u5168\u7247\u6700\u5927\u7b11\u70b9\u548c\u7ebf\u7d22", "created_at": "2012-12-05 13:11:31", "id": "265349110"}, {"rating": {"max": 5, "value": 5.0, "min": 0}, "useful_count": 0, "author": {"uid": "Bebefore", "avatar": "https://img3.doubanio.com\/icon\/u8460892-74.jpg", "signature": "\u751f\u6d3b\u662f\u4ec0\u4e48\u751f\u6d3b\u5c31\u662f\u80f8\u53e3\u788e\u5927\u77f3\u554a", "alt": "https:\/\/www.douban.com\/people\/Bebefore\/", "id": "8460892", "name": "\u6e38\u5766"}, "subject_id": "1303418", "content": "\u5230\u5904\u90fd\u662f\u673a\u7075\u4fcf\u76ae\u7684\u53f0\u8bcd\uff0c\u6296\u843d\u5728\u7ed3\u5b9e\u7684\u6545\u4e8b\u4e2d\uff0c\u559c\u5267\uff0c\u7406\u76f4\u6c14\u58ee\u7684\u7ad9\u5728\u6c89\u91cd\u7684\u9898\u6750\u91cc\u3002\u5403\u918b\u7684\u4e08\u592b\u5bf9\u7740\u59bb\u5b50\u7684\u60c5\u592b\u6012\u543c\uff1a\u201c\u73b0\u5728\u4f60\u7ad9\u5728\u6211\u7684\u62d6\u978b\u91cc\u8ddf\u6211\u8c08\u8bba\u7231\u56fd\uff1f\u6211\u7231\u6211\u7684\u7956\u56fd\uff0c\u4ee5\u53ca\u6211\u7684\u62d6\u978b\uff01\u201d\u62d6\u978b\u548c\u56fd\u5bb6\uff0c\u559c\u5267\u548c\u5386\u53f2\uff0c\u5728\u559c\u5267\u5bb6\u773c\u4e2d\uff0c\u4e00\u6837\u73cd\u8d35\u3002", "created_at": "2015-04-08 10:39:14", "id": "841009683"}, {"rating": {"max": 5, "value": 5.0, "min": 0}, "useful_count": 0, "author": {"uid": "3334785", "avatar": "https://img3.doubanio.com\/icon\/u3334785-6.jpg", "signature": "", "alt": "https:\/\/www.douban.com\/people\/3334785\/", "id": "3334785", "name": "swing in sun"}, "subject_id": "1303418", "content": "\u7d27\u5f20\u6263\u4eba\u5fc3\u5f26\u7684\u6218\u4e89\u6545\u4e8b\uff0c\u5374\u597d\u7b11\u53c8\u60ca\u53f9\u3002\u6ca1\u6709\u5927\u9053\u7406\uff0c\u6709\u6f14\u5458\u8d28\u6734\u7684\u53f0\u8bcd\u548c\u68a6\u60f3\u3002\u5218\u522b\u8c2670\u5e74\u524d\u7684\u540d\u4f5c\uff0c\u5f7c\u65f6\u8fd8\u5728\u6218\u65f6\uff0c\u82e6\u4e2d\u5e26\u7b11\u7684\u8fd9\u90e8\u4f5c\u54c1\uff0c\u591a\u4e48\u52b1\u5fd7\u52a8\u4eba\uff0c\u53c8\u5145\u6ee1\u5947\u601d\u548c\u73af\u73af\u76f8\u6263\u7684\u624d\u534e\u554a\u3002\u6f14\u5458\u5149\u534e\u7167\u4eba\u71a0\u71a0\u751f\u8f89\u554a\uff0c\u8d5e\u3002", "created_at": "2011-07-21 13:14:20", "id": "82082910"}, {"rating": {"max": 5, "value": 5.0, "min": 0}, "useful_count": 0, "author": {"uid": "aeirolu", "avatar": "https://img3.doubanio.com\/icon\/u1228483-1.jpg", "signature": "", "alt": "https:\/\/www.douban.com\/people\/aeirolu\/", "id": "1228483", "name": "Lo"}, "subject_id": "1303418", "content": "hia hia hia a real classic", "created_at": "2012-11-02 22:30:40", "id": "598601683"}, {"rating": {"max": 5, "value": 4.0, "min": 0}, "useful_count": 0, "author": {"uid": "4329212", "avatar": "https://img3.doubanio.com\/icon\/u4329212-6.jpg", "signature": "\u4e0d\u662f\u5f71\u8ff7\u662f\u7403\u8ff7", "alt": "https:\/\/www.douban.com\/people\/4329212\/", "id": "4329212", "name": "\u5341\u5e74"}, "subject_id": "1303418", "content": "\u5218\u522b\u8c26\u5f0f\u7684\u559c\u5267\u603b\u8ba9\u4eba\u60f3\u8d77\u8001\u5f0f\u7684\u56fd\u5916\u821e\u53f0\u559c\u5267\uff0c\u5938\u5f20\uff0c\u751f\u52a8\uff0c\u8bbd\u523a", "created_at": "2010-07-19 18:34:33", "id": "272543933"}, {"rating": {"max": 5, "value": 4.0, "min": 0}, "useful_count": 0, "author": {"uid": "beemer", "avatar": "https://img1.doubanio.com\/icon\/u1032065-47.jpg", "signature": "20091212", "alt": "https:\/\/www.douban.com\/people\/beemer\/", "id": "1032065", "name": "\u8521\u9e1f"}, "subject_id": "1303418", "content": "dolorously a  comedy", "created_at": "2011-03-07 11:27:21", "id": "362631922"}, {"rating": {"max": 5, "value": 5.0, "min": 0}, "useful_count": 0, "author": {"uid": "3693991", "avatar": "https://img3.doubanio.com\/icon\/u3693991-1.jpg", "signature": "", "alt": "https:\/\/www.douban.com\/people\/3693991\/", "id": "3693991", "name": "\u4f46\u6c42\u4e00\u9189"}, "subject_id": "1303418", "content": "\u6bd41983\u5e74\u7684\u7248\u672c\u5f3a\u592a\u591a\u4e86\u3002\u5361\u6d1b\u90ce\u767d\u771f\u662f\u5c24\u7269\u3001\u602a\u4e0d\u5f97\u8ba9\u76d6\u535a\u90fd\u5982\u6b64\u7740\u8ff7\u3002\u8fd9\u662f\u4e00\u90e8\u6c38\u8fdc\u4e0d\u4f1a\u88ab\u65f6\u5149\u63a9\u57cb\u7684\u597d\u620f\uff0c\u65e0\u8bba\u8fc7\u53bb\u591a\u5c11\u5e74\uff0c\u90fd\u4f1a\u8ba9\u89c2\u770b\u5b83\u7684\u5f71\u8ff7\u63a8\u5d07\u5907\u81f3\u3002\u8de8\u8d8a\u65f6\u4ee3\u3001\u8de8\u8d8a\u9636\u5c42\u3001\u8de8\u8d8a\u56fd\u522b\u8de8\u8d8a\u79cd\u65cf\uff0c\u8fd9\u5e94\u8be5\u662f\u7ecf\u5178\u6240\u5728\u5427\u3002", "created_at": "2012-05-08 01:13:19", "id": "529278453"}, {"rating": {"max": 5, "value": 5.0, "min": 0}, "useful_count": 1, "author": {"uid": "nopanic", "avatar": "https://img1.doubanio.com\/icon\/u1227727-27.jpg", "signature": "\u7279\u522b\u575a\u5f3a\u7684\u4e00\u4e2a\u4e8c\u59d0", "alt": "https:\/\/www.douban.com\/people\/nopanic\/", "id": "1227727", "name": "\u827e\u6817\u5b50"}, "subject_id": "1303418", "content": "\u6211\u5929\u53f0\u8bcd\u548c\u5267\u672c\u592a\u725b\u903c\u4e86\uff01\u771f\u559c\u6b22\u806a\u660e\u4eba\u7684\u4f5c\u54c1\u554a\u3002\u66f4\u725b\u903c\u7684\u662f\u5728\u6218\u65f6\u62cd\u8fd9\u6837\u7684\u7247\u5b50\u771f\u662f\u7545\u5feb\u6dcb\u6f13\uff0c\u5728\u5f00\u573a\u5c31\u901a\u8fc7\u9f99\u5957\u8bf4\u51fa\u4ed6\u81ea\u5df1\u7684\u8bdd\u201cA laugh is nothing to be sneezed at\u6c38\u8fdc\u4e0d\u8be5\u8f7b\u89c6\u7b11\u58f0\u201d\uff0c\u4e5f\u662f\u4ed6\u672c\u4eba\u6001\u5ea6\u5427\uff1a\u6c38\u8fdc\u7528\u5e7d\u9ed8\u5bf9\u6297\u82e6\u96be\u548c\u8352\u8bde\u3002\u7528\u8fd9\u6837\u7684\u6001\u5ea6\u63cf\u8ff0\u6218\u4e89\uff0c\u548c\u51af\u5185\u53e4\u7279\u5f88\u6c14\u8d28\u76f8\u901a\u4e86", "created_at": "2017-11-17 02:28:06", "id": "1272241269"}, {"rating": {"max": 5, "value": 5.0, "min": 0}, "useful_count": 0, "author": {"uid": "shouting", "avatar": "https://img1.doubanio.com\/icon\/u1142799-47.jpg", "signature": "\u62e5\u6709\u7684\u90fd\u662f\u4fa5\u5e78\u554a", "alt": "https:\/\/www.douban.com\/people\/shouting\/", "id": "1142799", "name": "\u611f\u6069\u8282\u7684\u5c0f\u706b\u9e21"}, "subject_id": "1303418", "content": "\u5218\u522b\u8c26\u5927\u795e\u3002\u3002\u7075\u52a8&\u6001\u5ea6\uff01To be or not to be\uff1f\u3002\u3002", "created_at": "2011-12-13 16:54:09", "id": "57796706"}, {"rating": {"max": 5, "value": 5.0, "min": 0}, "useful_count": 0, "author": {"uid": "tucaoneo", "avatar": "https://img1.doubanio.com\/icon\/u33558758-18.jpg", "signature": "\u4e0d\u80fd\u591f\u505c\u4e0b\u6765\u53ea\u6709\u6d41\u52a8", "alt": "https:\/\/www.douban.com\/people\/tucaoneo\/", "id": "33558758", "name": "\u5410=\u69fd\u3002\u5462=\u54e6"}, "subject_id": "1303418", "content": "Classic Lubitsch. Carol Lombard's last performance.", "created_at": "2012-10-03 08:03:48", "id": "586798175"}, {"rating": {"max": 5, "value": 5.0, "min": 0}, "useful_count": 0, "author": {"uid": "boliwawa", "avatar": "https://img3.doubanio.com\/icon\/u1112922-20.jpg", "signature": "\u9189\u6216\u9192\uff0c\u8fd9\u5ea7\u57ce\u90fd\u4f24\u900f\u4e86\u4f60\u7684\u5fc3", "alt": "https:\/\/www.douban.com\/people\/boliwawa\/", "id": "1112922", "name": "\u6cc9\u306e\u5411\u65e5\u8475"}, "subject_id": "1303418", "content": "\u5267\u672c\u592a\u5389\u5bb3\u4e86\u3002\u5584\u5ac9\u53c8\u81ea\u5927\u7684\u4e08\u592b\uff0c\u5c61\u5c61\u906d\u9047\u201c\u751f\u5b58\u6216\u662f\u6b7b\u4ea1\u201d\u7684\u7a98\u5883\u3002\u5de7\u5999\u5468\u65cb\u7684\u59bb\u5b50\u90a3\u6311\u9017\u7537\u4eba\u7684\u8a00\u8bed\uff0c\u5567\u5567\u3002\u9519\u4e2d\u9519\uff0c\u5047\u626e\u4e0e\u62c6\u7a7f\uff0c\u6700\u7ec8\u4e00\u4e2a\u56fd\u5bb6\uff0c\u9760\u201c\u611a\u8822\u7684\u6f14\u5458\u201d\u5f97\u4ee5\u62ef\u6551\u3002", "created_at": "2016-11-01 00:10:40", "id": "161848633"}, {"rating": {"max": 5, "value": 5.0, "min": 0}, "useful_count": 0, "author": {"uid": "liaozhai", "avatar": "https://img3.doubanio.com\/icon\/u13863979-13.jpg", "signature": "", "alt": "https:\/\/www.douban.com\/people\/liaozhai\/", "id": "13863979", "name": "\u6587\u674e"}, "subject_id": "1303418", "content": "\u54c8\u54c8\u54c8\u54c8  \u5218\u522b\u8c26  to be or not to be  that is a question", "created_at": "2012-08-27 22:09:56", "id": "573474920"}, {"rating": {"max": 5, "value": 5.0, "min": 0}, "useful_count": 0, "author": {"uid": "39072740", "avatar": "https://img3.doubanio.com\/icon\/u39072740-5.jpg", "signature": "", "alt": "https:\/\/www.douban.com\/people\/39072740\/", "id": "39072740", "name": "\u6768\u5149\u5f20"}, "subject_id": "1303418", "content": "\u5728\u73b0\u5b9e\u4e2d\u65e0\u6cd5\u62b5\u5fa1\u4f60\u7684\u6b8b\u66b4\uff0c\u90a3\u4e48\u5c31\u5728\u620f\u5267\u4e2d\u628a\u4f60\u641e\u6210\u4e00\u4e2a\u5c0f\u4e11\uff0c\u8fd9\u662f\u827a\u672f\u72ec\u6709\u7684\u529b\u91cf\uff0c\u4e00\u4f19\u7535\u5f71\u4eba\u5728\u7535\u5f71\u91cc\u7528\u7535\u5f71\u7684\u65b9\u5f0f\u53cd\u6297\u4fb5\u7565\u8005\uff0c\u7acb\u610f\u5947\u5999\uff0c\u60c5\u6000\u611f\u4eba\uff0c\u559c\u5267\u6865\u6bb5\u66f4\u662f\u7ecf\u5178\uff0c\u7535\u5f71\u62cd\u6444\u4e8e\u4e8c\u6218\u5982\u706b\u5982\u837c\u76841942\u5e74\uff0c\u73b0\u5b9e\u4e0e\u827a\u672f\u7ed3\u5408\u7684\u5178\u8303\uff0c\u5728\u6606\u6c40\u7684\u65e0\u803b\u6df7\u86cb\u91cc\u6709\u5267\u9662\u91cc\u6740\u6389\u5e0c\u7279\u52d2\u7684\u60c5\u8282\uff0c\u660e\u663e\u5728\u5411\u5148\u9a71\u5218\u522b\u8c26\u81f4", "created_at": "2014-01-01 14:21:41", "id": "756112415"}, {"rating": {"max": 5, "value": 5.0, "min": 0}, "useful_count": 3, "author": {"uid": "lingXmin", "avatar": "https://img1.doubanio.com\/icon\/u3639251-798.jpg", "signature": "\u4f60\u5f00\u5fc3\u5c31\u597d\u5462(*^__^*)", "alt": "https:\/\/www.douban.com\/people\/lingXmin\/", "id": "3639251", "name": "\u4eba\u8089\u9972\u6599\u4f9b\u5e94\u5546"}, "subject_id": "1303418", "content": "Heil!myself!!!!!", "created_at": "2012-03-09 21:13:38", "id": "506114894"}, {"rating": {"max": 5, "value": 5.0, "min": 0}, "useful_count": 0, "author": {"uid": "kid007spy", "avatar": "https://img3.doubanio.com\/icon\/u3110845-21.jpg", "signature": "\u5c71\u897f\u7164\u77ff\u5927\u738b", "alt": "https:\/\/www.douban.com\/people\/kid007spy\/", "id": "3110845", "name": "\u738b\u6076"}, "subject_id": "1303418", "content": "\u7535\u5f71\u6700\u795e\u5947\u4e4b\u5904\u5c31\u662f\u770b\u8fc7\u7684\u955c\u5934\u518d\u770b\u4e00\u904d\u5fc5\u5b9a\u4f1a\u60f3\u8d77\u6765\u3002\u6240\u4ee5\uff0c\u4e3a\u4ec0\u4e48\u4e0a\u8bfe\u4e0d\u597d\u597d\u770b\u7247\u554a\uff01\uff01\uff01", "created_at": "2013-03-06 19:26:17", "id": "642070213"}, {"rating": {"max": 5, "value": 5.0, "min": 0}, "useful_count": 0, "author": {"uid": "3114482", "avatar": "https://img1.doubanio.com\/icon\/u3114482-78.jpg", "signature": "\u3067\u3082\u3001\u7a7a\u306b\u5730\u9762\u306f\u3042\u308a\u307e\u305b\u3093\u3088", "alt": "https:\/\/www.douban.com\/people\/3114482\/", "id": "3114482", "name": "ample"}, "subject_id": "1303418", "content": "\u4e00\u4e2a\u5b8c\u7f8e\u4e14\u738b\u9053\u7684\u5267\u672c\u5bf9\u4e00\u90e8\u559c\u5267\u7535\u5f71\u7684\u610f\u4e49\u4e0d\u8a00\u800c\u55bb\u2026\u2026", "created_at": "2011-03-24 22:24:41", "id": "369749516"}, {"rating": {"max": 5, "value": 5.0, "min": 0}, "useful_count": 0, "author": {"uid": "ophelia99", "avatar": "https://img3.doubanio.com\/icon\/u43877069-130.jpg", "signature": "\u65f6\u95f4\u6bd4\u4f60\u91cd\u8981", "alt": "https:\/\/www.douban.com\/people\/ophelia99\/", "id": "43877069", "name": "qurra"}, "subject_id": "1303418", "content": "\u559c\u5267\u7684\u9b45\u529b\uff0c\u5927\u4e00\u5bd2\u5047\u524d\u96be\u5fd8\u7684\u89c2\u5f71\u7ecf\u5386", "created_at": "2010-07-27 09:17:23", "id": "275360450"}], "start": 0, "total": 4804, "next_start": 100, "subject": {"rating": {"max": 10, "average": 9.2, "details": {"1": 14.0, "3": 461.0, "2": 35.0, "5": 6036.0, "4": 2728.0}, "stars": "45", "min": 0}, "genres": ["\u559c\u5267", "\u6218\u4e89"], "title": "\u4f60\u9003\u6211\u4e5f\u9003", "casts": [{"avatars": {"small": "https://img1.doubanio.com\/view\/celebrity\/s_ratio_celebrity\/public\/p1397441741.19.jpg", "large": "https://img1.doubanio.com\/view\/celebrity\/s_ratio_celebrity\/public\/p1397441741.19.jpg", "medium": "https://img1.doubanio.com\/view\/celebrity\/s_ratio_celebrity\/public\/p1397441741.19.jpg"}, "name_en": "Carole Lombard", "name": "\u5361\u6d1b\u00b7\u6717\u767d", "alt": "https:\/\/movie.douban.com\/celebrity\/1027901\/", "id": "1027901"}, {"avatars": {"small": "https://img3.doubanio.com\/view\/celebrity\/s_ratio_celebrity\/public\/p24271.jpg", "large": "https://img3.doubanio.com\/view\/celebrity\/s_ratio_celebrity\/public\/p24271.jpg", "medium": "https://img3.doubanio.com\/view\/celebrity\/s_ratio_celebrity\/public\/p24271.jpg"}, "name_en": "Jack Benny", "name": "\u6770\u514b\u00b7\u672c\u5c3c", "alt": "https:\/\/movie.douban.com\/celebrity\/1004930\/", "id": "1004930"}, {"avatars": {"small": "https://img3.doubanio.com\/view\/celebrity\/s_ratio_celebrity\/public\/p49124.jpg", "large": "https://img3.doubanio.com\/view\/celebrity\/s_ratio_celebrity\/public\/p49124.jpg", "medium": "https://img3.doubanio.com\/view\/celebrity\/s_ratio_celebrity\/public\/p49124.jpg"}, "name_en": "Robert Stack", "name": "\u7f57\u4f2f\u7279\u00b7\u65af\u5854\u514b", "alt": "https:\/\/movie.douban.com\/celebrity\/1013972\/", "id": "1013972"}], "durations": ["99 \u5206\u949f"], "collect_count": 14676, "mainland_pubdate": "", "has_video": true, "original_title": "To Be or Not to Be", "subtype": "movie", "directors": [{"avatars": {"small": "https://img3.doubanio.com\/view\/celebrity\/s_ratio_celebrity\/public\/p3142.jpg", "large": "https://img3.doubanio.com\/view\/celebrity\/s_ratio_celebrity\/public\/p3142.jpg", "medium": "https://img3.doubanio.com\/view\/celebrity\/s_ratio_celebrity\/public\/p3142.jpg"}, "name_en": "Ernst Lubitsch", "name": "\u6069\u65af\u7279\u00b7\u5218\u522b\u8c26", "alt": "https:\/\/movie.douban.com\/celebrity\/1007140\/", "id": "1007140"}], "pubdates": ["1942-03-06"], "year": "1942", "images": {"small": "https://img3.doubanio.com\/view\/photo\/s_ratio_poster\/public\/p1339915772.jpg", "large": "https://img3.doubanio.com\/view\/photo\/s_ratio_poster\/public\/p1339915772.jpg", "medium": "https://img3.doubanio.com\/view\/photo\/s_ratio_poster\/public\/p1339915772.jpg"}, "alt": "https:\/\/movie.douban.com\/subject\/1303418\/", "id": "1303418"}}